{
  "不善负重": {
    "1": "背负重物毫无技巧，最大负重降低20%。",
    "2": "背负重物毫无技巧，最大负重降低40%。",
    "3": "背负重物毫无技巧，最大负重降低60%。"
  },
  "不幸者": {
    "3": "十里八村有名的倒霉催，掉落稀有物品的概率降低50%"
  },
  "不擅肉搏": {
    "1": "很不擅长近身肉搏，对5米内的敌人伤害降低5%。",
    "2": "很不擅长近身肉搏，对5米内的敌人伤害降低10%。",
    "3": "很不擅长近身肉搏，对5米内的敌人伤害降低15%。"
  },
  "不擅远程": {
    "1": "很不擅长远程打击，对20米外的敌人伤害降低5%。",
    "2": "很不擅长远程打击，对20米外的敌人伤害降低10%。",
    "3": "很不擅长远程打击，对20米外的敌人伤害降低15%。"
  },
  "不易察觉": {
    "1": "擅于伪装不易察觉，被敌人发现时警戒增长速度降低20%。",
    "2": "擅于伪装不易察觉，被敌人发现时警戒增长速度降低40%。",
    "3": "擅于伪装不易察觉，被敌人发现时警戒增长速度降低60%。"
  },
  "不焚者": {
    "3": "被部落族人视为异类的存在皮肤结构异于常人，被施加烧伤或点燃后不会受到相应的效果影响。"
  },
  "两败俱伤": {
    "1": "以痛苦换取力量，被攻击到弱点部位时有25%概率15s内对敌人的弱点部位伤害提升20%，但自己的弱点受到伤害也会提升20%。持续15s（冷却时间25s）",
    "2": "以痛苦换取力量，被攻击到弱点部位时有25%概率15s内对敌人的弱点部位伤害提升40%，但自己的弱点受到伤害也会提升40%。持续15s（冷却时间25s）",
    "3": "以痛苦换取力量，被攻击到弱点部位时有25%概率15s内对敌人的弱点部位伤害提升60%，但自己的弱点受到伤害也会提升60%。持续15s（冷却时间25s）"
  },
  "以攻代守": {
    "1": "成功闪避敌人攻击后，在4秒内使自己的攻击无法被弹反，并使自己的任意武器攻击能够弹反敌人的攻击。",
    "2": "成功闪避敌人攻击后，在6秒内使自己的攻击无法被弹反，并使自己的任意武器攻击能够弹反敌人的攻击。",
    "3": "成功闪避敌人攻击后，在8秒内使自己的攻击无法被弹反，并使自己的任意武器攻击能够弹反敌人的攻击。"
  },
  "以牙还牙": {
    "1": "【利爪专属】感受痛苦强势回击，受到攻击时有20%的概率触发能够在4s内累积伤害，在此期间攻击到敌人时将对其释放当前累积到的所有伤害（冷却时间30s）。",
    "2": "【利爪专属】感受痛苦强势回击，受到攻击时有20%的概率触发能够在6s内累积伤害，在此期间攻击到敌人时将对其释放当前累积到的所有伤害（冷却时间30s）。",
    "3": "【利爪专属】感受痛苦强势回击，受到攻击时有20%的概率触发能够在8s内累积伤害，在此期间攻击到敌人时将对其释放当前累积到的所有伤害（冷却时间30s）。"
  },
  "伐木巧手": {
    "1": "【毒牙专属】伐木不自其本，砍伐过的树木再生时间缩短20%。",
    "2": "【毒牙专属】伐木不自其本，砍伐过的树木再生时间缩短30%。",
    "3": "【毒牙专属】伐木不自其本，砍伐过的树木再生时间缩短40%。"
  },
  "伤害共鸣·攻": {
    "1": "攻击命中目标时有10%概率触发，提升自身「伤害提升」与「伤害减免」中较低的一项，幅度为较高项的50%，持续12秒。（冷却时间60秒）",
    "2": "攻击命中目标时有15%概率触发，提升自身「伤害提升」与「伤害减免」中较低的一项，幅度为较高项的50%，持续12秒。（冷却时间45秒）",
    "3": "攻击命中目标时有20%概率触发，提升自身「伤害提升」与「伤害减免」中较低的一项，幅度为较高项的50%，持续12秒。（冷却时间30秒）"
  },
  "伤害共鸣·防": {
    "1": "防御敌人攻击时有15%概率触发，提升自身「伤害提升」与「伤害减免」中较低的一项，幅度为较高项的50%，持续12秒。（冷却时间60秒）",
    "2": "防御敌人攻击时有20%概率触发，提升自身「伤害提升」与「伤害减免」中较低的一项，幅度为较高项的50%，持续12秒。（冷却时间45秒）",
    "3": "防御敌人攻击时有25%概率触发，提升自身「伤害提升」与「伤害减免」中较低的一项，幅度为较高项的50%，持续12秒。（冷却时间30秒）"
  },
  "伤害流转·攻": {
    "1": "攻击命中目标时有5%概率触发，将当前的全部「伤害减免」按50%比例转化为「伤害提升」，持续12秒。（冷却时间60秒）",
    "2": "攻击命中目标时有10%概率触发，将当前的全部「伤害减免」按50%比例转化为「伤害提升」，持续12秒。（冷却时间45秒）",
    "3": "攻击命中目标时有15%概率触发，将当前的全部「伤害减免」按50%比例转化为「伤害提升」，持续12秒。（冷却时间30秒）"
  },
  "伤害流转·防": {
    "1": "防御敌人攻击时有10%概率触发，将当前一半的「伤害提升」转化为「伤害减免」，持续12秒。（冷却时间60秒）",
    "2": "防御敌人攻击时有15%概率触发，将当前一半的「伤害提升」转化为「伤害减免」，持续12秒。（冷却时间45秒）",
    "3": "防御敌人攻击时有20%概率触发，将当前一半的「伤害提升」转化为「伤害减免」，持续12秒。（冷却时间30秒）"
  },
  "伺机连袭": {
    "1": "成功闪避敌人攻击后，获得1层持续3秒的「连袭」状态：下一次从背后发动的武器攻击依据层数额外造成相应次数的伤害。至多叠加2层。",
    "2": "成功闪避敌人攻击后，获得1层持续3秒的「连袭」状态：下一次从背后发动的武器攻击依据层数额外造成相应次数的伤害。至多叠加3层。",
    "3": "成功闪避敌人攻击后，获得1层持续3秒的「连袭」状态：下一次从背后发动的武器攻击依据层数额外造成相应次数的伤害。至多叠加4层。"
  },
  "体力窃取": {
    "1": "【猎手专属】攻击命中目标时有5%概率触发，窃取目标当前10%的最大体力（至多30点），转化为自身的提升，持续12秒，至多叠加5层。",
    "2": "【猎手专属】攻击命中目标时有10%概率触发，窃取目标当前10%的最大体力（至多30点），转化为自身的提升，持续12秒，至多叠加5层。",
    "3": "【猎手专属】攻击命中目标时有15%概率触发，窃取目标当前10%的最大体力（至多30点），转化为自身的提升，持续12秒，至多叠加5层。"
  },
  "体力虹吸": {
    "1": "攻击命中目标时有5%概率触发，使其在12秒内每次攻击额外消耗10点体力为施加者恢复10点体力。",
    "2": "攻击命中目标时有10%概率触发，使其在12秒内每次攻击额外消耗15点体力为施加者恢复15点体力。",
    "3": "攻击命中目标时有15%概率触发，使其在12秒内每次攻击额外消耗20点体力为施加者恢复20点体力。"
  },
  "体能充沛": {
    "1": "体力恢复效率更高，每次恢复体力时可以获得本次恢复量15%的额外恢复。",
    "2": "体力恢复效率更高，每次恢复体力时可以获得本次恢复量25%的额外恢复。",
    "3": "体力恢复效率更高，每次恢复体力时可以获得本次恢复量50%的额外恢复。"
  },
  "体能枯竭": {
    "1": "身心懒惰，体力恢复量降低20%。",
    "2": "身心懒惰，体力恢复量降低30%。",
    "3": "身心懒惰，体力恢复量降低50%。"
  },
  "余烬": {
    "1": "生命耗尽时不会进入濒死， 在8秒内可额外承受3次致死攻击，效果时间内次数耗尽则立即死亡。(冷却时间45秒）",
    "2": "生命耗尽时不会进入濒死，在10秒内可额外承受6次致死攻击，效果时间内次数耗尽则立即死亡。(冷却时间45秒）",
    "3": "生命耗尽时不会进入濒死， 在12秒内可额外承受9次致死攻击，效果时间内次数耗尽则立即死亡。(冷却时间45秒）"
  },
  "先攻": {
    "1": "攻击目标后背时额外附加20点昏迷伤害。（冷却时间10秒）",
    "2": "攻击目标后背时额外附加35点昏迷伤害。（冷却时间7.5秒）",
    "3": "攻击目标后背时额外附加50点昏迷伤害。（冷却时间5秒）"
  },
  "免伤祈佑": {
    "1": "受到攻击时有5%概率触发，在8秒内敌人对自己造成的伤害始终按最低值进行计算。（冷却时间30秒）",
    "2": "受到攻击时有10%概率触发，在10秒内敌人对自己造成的伤害始终按最低值进行计算。（冷却时间30秒）",
    "3": "受到攻击时有15%概率触发，在12秒内敌人对自己造成的伤害始终按最低值进行计算。（冷却时间30秒）"
  },
  "免伤窃取": {
    "1": "【蛮角专属】攻击命中目标时有5%概率触发，窃取目标10%的伤害减免，转化为自身的提升，持续12秒，至多叠加5层。",
    "2": "【蛮角专属】攻击命中目标时有10%概率触发，窃取目标10%的伤害减免，转化为自身的提升，持续12秒，至多叠加5层。",
    "3": "【蛮角专属】攻击命中目标时有15%概率触发，窃取目标10%的伤害减免，转化为自身的提升，持续12秒，至多叠加5层。"
  },
  "全盛战意": {
    "1": "攻击命中目标时若自身生命值、韧性值全满，则获得4秒「以攻代守」状态：期间自己的攻击无法被弹反，并使自己的任意武器攻击也能够弹反敌人的攻击。（冷却时间25秒）",
    "2": "攻击命中目标时若自身生命值、韧性值全满，则获得6秒「以攻代守」状态：期间自己的攻击无法被弹反，并使自己的任意武器攻击也能够弹反敌人的攻击。（冷却时间25秒）",
    "3": "攻击命中目标时若自身生命值、韧性值全满，则获得8秒「以攻代守」状态：期间自己的攻击无法被弹反，并使自己的任意武器攻击也能够弹反敌人的攻击。（冷却时间25秒）"
  },
  "全盛状态": {
    "1": "攻击命中目标时若自身生命值、韧性值全满，则获得12秒全盛状态，在此期间暴击伤害提升50%，并且自身不会被暴击。（冷却时间60秒）",
    "2": "攻击命中目标时若自身生命值、韧性值全满，则获得12秒全盛状态，在此期间暴击伤害提升50%，并且自身不会被暴击。（冷却时间45秒）",
    "3": "攻击命中目标时若自身生命值、韧性值全满，则获得12秒全盛状态，在此期间暴击伤害提升50%，并且自身不会被暴击。（冷却时间30秒）"
  },
  "减轻伤势": {
    "1": "皮糙肉厚天生抗揍，受到伤害降低3%。",
    "2": "皮糙肉厚天生抗揍，受到伤害降低6%。",
    "3": "皮糙肉厚天生抗揍，受到伤害降低9%。"
  },
  "出血抑制": {
    "1": "【毒牙专属】凝血速度异于常人，在受到攻击时有5%的概率触发，移除自身的流血效果并在12秒内不会受到流血效果影响（冷却时间30s）。",
    "2": "【毒牙专属】凝血速度异于常人，在受到攻击时有10%的概率触发，移除自身的流血效果并在12秒内不会受到流血效果影响（冷却时间30s）。",
    "3": "【毒牙专属】凝血速度异于常人，在受到攻击时有15%的概率触发，移除自身的流血效果并在12秒内不会受到流血效果影响（冷却时间30s）。"
  },
  "出身·劳动慢热": {
    "1": "族人中频出能工巧匠不擅苦力，受族人影响，学习伐木、采矿、种植、采收的熟练度成长速度降低25%。",
    "2": "族人中少有做粗活的人，从小耳濡目染，学习伐木、采矿、种植、采收的熟练度成长速度降低35%。",
    "3": "出生于富裕的氏族自年少时就非常厌恶做苦力，学习伐木、采矿、种植、采收的熟练度成长速度降低50%。"
  },
  "出身·匠人": {
    "1": "出生于一个工匠氏族，从小耳濡目染，学习工匠、炼金、武器制造、防具制造、烹饪的熟练度成长速度提升50%。",
    "2": "族人中曾诞生过很多有名的工匠，在名匠熏陶下，学习工匠、炼金、武器制造、防具制造、烹饪的熟练度成长速度提升60%。",
    "3": "年少时就展现出了过人的制造天份而备受期待，学习工匠、炼金、武器制造、防具制造、烹饪的熟练度成长速度提升75%。"
  },
  "出身·手工慢热": {
    "1": "完全没有遗传氏族中的匠人基因，学习工匠、炼金、武器制造、防具制造、烹饪的熟练度成长速度降低25%。",
    "2": "族人信奉慢工出细活，从小耳濡目染，学习工匠、炼金、武器制造、防具制造、烹饪的熟练度成长速度降低35%。",
    "3": "是一个糙汉，精细的手工打造完全不适合自己，学习工匠、炼金、武器制造、防具制造、烹饪的熟练度成长速度降低50%。"
  },
  "出身·护卫": {
    "1": "在一群氏族守卫的环绕下成长，从小耳濡目染，学习大剑、刀、矛、盾、弓类武器的熟练度成长速度提升50%。",
    "2": "氏族中有很多守夜卫士，带着年少的你在漫长黑夜中磨练技艺，学习大剑、刀、矛、盾、弓类武器的熟练度成长速度提升60%。",
    "3": "曾担任过数任神庙卫士，因武艺精湛而备受重用，学习大剑、刀、矛、盾、弓类武器的熟练度成长速度提升75%。"
  },
  "出身·拙劣生存·I": {
    "1": "在亲人拙劣得生存技巧下长大，从小耳濡目染学习医疗、游泳、攀爬的熟练度成长速度降低25%。"
  },
  "出身·拙劣生存·II": {
    "2": "在亲人拙劣得生存技巧下长大，从小耳濡目染学习医疗、游泳、攀爬的熟练度成长速度降低35%。"
  },
  "出身·拙劣生存·III": {
    "3": "在亲人拙劣得生存技巧下长大，从小耳濡目染学习医疗、游泳、攀爬的熟练度成长速度降低50%。"
  },
  "出身·搏斗": {
    "1": "出生于一个战士氏族，从小耳濡目染，学习刀，双刀，锤，大剑，拳套类武器的熟练度成长速度提升50%。",
    "2": "族人中有很多小有名气的战士，擅长近身搏斗，从小耳濡目染学习刀，双刀，锤，大剑，拳套类武器的熟练度成长速度提升60%。",
    "3": "族人中曾诞生过赫赫有名的战士，这份荣耀延续至今，学习刀，双刀，锤，大剑，拳套类武器的熟练度成长速度提升75%。"
  },
  "出身·杂工": {
    "1": "氏族中学徒颇多，从小耳濡目染，学习纺织、制陶、木石、制皮、烧窑的熟练度成长速度提升50%。",
    "2": "族人曾教过很多的杂工经验和技巧，这是一种传承，学习纺织、制陶、木石、制皮、烧窑的熟练度成长速度提升60%。",
    "3": "对于杂工的适应能力极强，手脚麻利，学习纺织、制陶、木石、制皮、烧窑的熟练度成长速度提升75%。"
  },
  "出身·杂活慢热": {
    "1": "氏族中有很多杂工，但自己是个特立独行不愿随波逐流的人，学习纺织、木石、制皮、制陶、烧窑的熟练度成长速度降低25%。",
    "2": "族人都是一群差劲的杂工，从小耳濡目染，学习纺织、木石、制皮、制陶、烧窑的熟练度成长速度降低35%。",
    "3": "年少时便对重复且枯燥的杂活敬而远之，学习纺织、木石、制皮、制陶、烧窑的熟练度成长速度降低50%。"
  },
  "出身·沉迷护卫": {
    "1": "年少时曾经历过惨痛的教训，导致专注于护卫能力提升而忽略了其他技艺，学习双刀，拳套，锤类武器的熟练度成长速度降低25%。",
    "2": "曾被族人痛斥护卫能力的不足，受其影响，学习双刀，拳套，锤类武器的熟练度成长速度降低35%。",
    "3": "自己是一个古板的人，沉迷于提升护卫能力而疏于其他技艺的磨练，学习双刀，拳套，锤类武器的熟练度成长速度降低50%。"
  },
  "出身·沉迷搏斗": {
    "1": "时常受到族人的打压为了反抗压迫，专注于搏斗能力的提升而忽略了其他技艺，学习矛，弓，盾类武器的熟练度成长速度降低25%。",
    "2": "被强大战士的光环笼罩是痛苦的，想变得更强大但忽略了其他能力的成长，学习矛，弓，盾类武器的熟练度成长速度降低35%。",
    "3": "曾被族中的强者误导，导致错误的成长路线只专注于近身搏斗而疏于其他技艺的磨练，学习矛，弓，盾类武器的熟练度成长速度降低50%。"
  },
  "出身·沉迷狩猎": {
    "1": "年少时曾展现出一点猎手天份，导致成长路线偏激而忽略了其他能力的成长，学习大剑，盾，锤类武器的熟练度成长速度降低25%。",
    "2": "常年被族人怒斥狩猎技巧粗糙，导致拼命提升猎手能力而疏于其他技艺的磨练，学习大剑，盾，锤类武器的熟练度成长速度降低35%。",
    "3": "自己是一个倔强的猎手，执着于提升狩猎能力而疏于其他技艺的磨练，学习大剑，盾，锤类武器的熟练度成长速度降低50%。"
  },
  "出身·狩猎": {
    "1": "出生于一个猎人氏族，从小耳濡目染学习弓，矛，刀，双刀，拳套类武器的熟练度成长速度提升50%。",
    "2": "族人中有很多小有名气的猎手，擅长给予猎物致命一击，从小耳濡目染学习弓，矛，刀，双刀，拳套类武器的熟练度成长速度提升60%。",
    "3": "族人中曾出过多名传奇猎人，在猎人基因的影响下，学习弓，矛，刀，双刀，拳套类武器的熟练度成长速度提升75%。"
  },
  "出身·生存": {
    "1": "亲人有着出色的生存技巧，从小耳濡目染学习医疗、游泳、攀爬的熟练度成长速度大幅度提升。",
    "2": "亲人有着出色的生存技巧，从小耳濡目染学习医疗、游泳、攀爬的熟练度成长速度很大幅度提升。",
    "3": "亲人有着出色的生存技巧，从小耳濡目染学习医疗、游泳、攀爬的熟练度成长速度超大幅度提升。"
  },
  "出身·苦力": {
    "1": "出生于一个地位卑微资源匮乏的氏族，只能依靠苦力生存，学习伐木、采矿、种植、采收的熟练度成长速度提升50%。",
    "2": "氏族衰败族人靠做苦力将自己养大，从小耳濡目染，学习伐木、采矿、种植、采收的熟练度成长速度提升60%。",
    "3": "在努力生存的过程中积累了大量做苦力的经验，掌握着丰富且实用的做工技巧，学习伐木、采矿、种植、采收的熟练度成长速度提升75%。"
  },
  "切石加速": {
    "1": "切石熟手，完成切石工作的时间缩短10%。",
    "2": "切石熟手，完成切石工作的时间缩短20%。",
    "3": "切石熟手，完成切石工作的时间缩短30%。"
  },
  "制甲专注": {
    "1": "【匠人专属】制作防具时异常专注，产出高品质概率提升5%。",
    "2": "【匠人专属】制作防具时异常专注，产出高品质概率提升7.5%。",
    "3": "【匠人专属】制作防具时异常专注，产出高品质概率提升10%。"
  },
  "制皮加速": {
    "1": "【杂工专属】制皮能手，完成制皮工作的时间缩短10%。",
    "2": "【杂工专属】制皮能手，完成制皮工作的时间缩短20%。",
    "3": "【杂工专属】制皮能手，完成制皮工作的时间缩短30%。"
  },
  "制陶加速": {
    "1": "【杂工专属】对制陶工艺运用自如，完成制陶工作的时间缩短10%。",
    "2": "【杂工专属】对制陶工艺运用自如，完成制陶工作的时间缩短20%。",
    "3": "【杂工专属】对制陶工艺运用自如，完成制陶工作的时间缩短30%。"
  },
  "刺鞭增伤": {
    "1": "使用刺鞭威力更强，刺鞭类武器造成的伤害提升3%。",
    "2": "使用刺鞭威力更强，刺鞭类武器造成的伤害提升6%。",
    "3": "使用刺鞭威力更强，刺鞭类武器造成的伤害提升9%。"
  },
  "加重伤势": {
    "1": "身体脆弱极易受伤，受到的伤害提高3%。",
    "2": "身体脆弱极易受伤，受到的伤害提高6%。",
    "3": "身体脆弱极易受伤，受到的伤害提高9%。"
  },
  "动脉破坏": {
    "1": "攻击处于流血状态的目标有5%概率触发，使其流血伤害大幅增加，持续8秒。",
    "2": "攻击处于流血状态的目标有10%概率触发，使其流血伤害大幅增加，持续8秒。",
    "3": "攻击处于流血状态的目标有15%概率触发，使其流血伤害大幅增加，持续8秒。"
  },
  "劳动狂人": {
    "3": "像机器一样不知疲倦甚至让人担心精神状态是否正常，最大精神提高100%"
  },
  "势大力沉": {
    "1": "【利爪专属】每一击都势大力沉，对目标造成伤害时额外消耗15体力以使本次伤害提升5%，并额外消耗目标5点体力。",
    "2": "【利爪专属】每一击都势大力沉，对目标造成伤害时额外消耗15体力以使本次伤害提升10%，并额外消耗目标7.5点体力。",
    "3": "【利爪专属】每一击都势大力沉，对目标造成伤害时额外消耗15体力以使本次伤害提升15%，并额外消耗目标10点体力。"
  },
  "勇气传递": {
    "1": "自身获得持续效果时有10%概率触发，6秒内将自身的部分持续效果传递给15米范围内的友方单位。（冷却时间25秒）",
    "2": "自身获得持续效果时有15%概率触发，8秒内将自身的部分持续效果传递给15米范围内的友方单位。（冷却时间25秒）",
    "3": "自身获得持续效果时有20%概率触发，10秒内将自身的部分持续效果传递给15米范围内的友方单位。（冷却时间25秒）"
  },
  "勇气激流": {
    "1": "攻击命中目标时有5%概率触发，清除自身天赋的冷却状态。（冷却时间60秒）",
    "2": "攻击命中目标时有10%概率触发，清除自身天赋的冷却状态。（冷却时间45秒）",
    "3": "攻击命中目标时有15%概率触发，清除自身天赋的冷却状态。（冷却时间30秒）"
  },
  "化解危机": {
    "1": "没点绝活怎么在这片土地生存，有15%的概率触发，受到攻击时使本次伤害至多失去5%最大生命（受到伤害超过生命上限时无法生效）。",
    "2": "没点绝活怎么在这片土地生存，有15%的概率触发，受到攻击时使本次伤害至多失去4%最大生命（受到伤害超过生命上限时无法生效）。",
    "3": "没点绝活怎么在这片土地生存，有15%的概率触发，受到攻击时使本次伤害至多失去3%最大生命（受到伤害超过生命上限时无法生效）。"
  },
  "单刀减伤": {
    "1": "使用单刀威胁减弱，使用刀类武器造成的伤害降低10%。",
    "2": "使用单刀威胁减弱，使用刀类武器造成的伤害降低15%。",
    "3": "使用单刀威胁减弱，使用刀类武器造成的伤害降低20%。"
  },
  "单刀增伤": {
    "1": "使用单刀威力更强，单刀类武器造成的伤害提升3%。",
    "2": "使用单刀威力更强，单刀类武器造成的伤害提升6%。",
    "3": "使用单刀威力更强，单刀类武器造成的伤害提升9%。"
  },
  "危机反应": {
    "2": "受到攻击时有20%概率触发，防御提升5%、最大生命提升5%，持续30s。（冷却时间50s）"
  },
  "厌恶下雨": {
    "3": "雨天使人烦躁，下雨时心情值下降6点，并在5分钟内心情值下降速率提升100%，获得心情值时降低60%。（在此期间可使心情达到非常沮丧状态）"
  },
  "厌恶下雪": {
    "3": "雪天的一切都让人厌烦，下雪时心情值下降6点，并在5分钟内心情值下降速率提升100%，获得心情值时降低60%。（在此期间可使心情达到非常沮丧状态）"
  },
  "厌恶主食": {
    "3": "吃到主食时异常厌恶，心情值下降6点，并在5分钟内心情值下降速率提升100%，获得心情值时降低60%。（在此期间可使心情达到非常沮丧状态）"
  },
  "厌恶动物": {
    "3": "附近存在任何动物都会心生厌恶，心情值下降6点，并在5分钟内心情值下降速率提升100%，获得心情值时降低60%。（在此期间可使心情达到非常沮丧状态）"
  },
  "厌恶寒冷": {
    "3": "对温度非常敏感，身处寒冷的环境温度中时，心情值下降6点，并在5分钟内心情值下降速率提升100%，获得心情值时降低60%。（在此期间可使心情达到非常沮丧状态）"
  },
  "厌恶巨象": {
    "3": "附近有巨象时心生厌恶，心情值下降6点，并在5分钟内心情值下降速率提升100%，获得心情值时降低60%。（在此期间可使心情达到非常沮丧状态）"
  },
  "厌恶布制衣物": {
    "3": "厌恶粗滥的服饰，装备布制衣物时，心情值下降6点，并在5分钟内心情值下降速率提升100%，获得心情值时降低60%。（在此期间可使心情达到非常沮丧状态）"
  },
  "厌恶平庸首领": {
    "3": "该蛮人追随的首领是红色以下品质时会心生厌恶，心情值下降6点，并在5分钟内心情值下降速率提升100%，获得心情值时降低60%。（在此期间可使心情达到非常沮丧状态）"
  },
  "厌恶晴天": {
    "3": "晴朗的天气让人感到不适，晴天时心情值下降6点，并在5分钟内心情值下降速率提升100%，获得心情值时降低60%。（在此期间可使心情达到非常沮丧状态）"
  },
  "厌恶果蔬": {
    "3": "吃到果蔬时，心情值下降6点，并在5分钟内心情值下降速率提升100%，获得心情值时降低60%。（在此期间可使心情达到非常沮丧状态）"
  },
  "厌恶水域": {
    "3": "生活区域周围有水域时，心情值下降6点，并在5分钟内心情值下降速率提升100%，获得心情值时降低60%。（在此期间可使心情达到非常沮丧状态）"
  },
  "厌恶河马": {
    "3": "附近有河马时心生厌恶，心情值下降6点，并在5分钟内心情值下降速率提升100%，获得心情值时降低60%。（在此期间可使心情达到非常沮丧状态）"
  },
  "厌恶洗澡": {
    "3": "厌恶被水浸湿的感觉，洗澡时心情值下降6点，并在5分钟内心情值下降速率提升100%，获得心情值时降低60%。（在此期间可使心情达到非常沮丧状态）"
  },
  "厌恶清寒": {
    "3": "对温度非常敏感，身处清寒的环境温度中时，心情值下降6点，并在5分钟内心情值下降速率提升100%，获得心情值时降低60%。（在此期间可使心情达到非常沮丧状态）"
  },
  "厌恶温热": {
    "3": "对温度非常敏感，身处温热的环境温度中时，心情值下降6点，并在5分钟内心情值下降速率提升100%，获得心情值时降低60%。（在此期间可使心情达到非常沮丧状态）"
  },
  "厌恶火烈鸟": {
    "3": "附近有火烈鸟时心生厌恶，心情值下降6点，并在5分钟内心情值下降速率提升100%，获得心情值时降低60%。（在此期间可使心情达到非常沮丧状态）"
  },
  "厌恶炎热": {
    "3": "对温度非常敏感，身处炎热的环境温度中时，心情值下降6点，并在5分钟内心情值下降速率提升100%，获得心情值时降低60%。（在此期间可使心情达到非常沮丧状态）"
  },
  "厌恶烟草": {
    "3": "厌恶烟草的味道，吸食烟草时，心情值下降6点，并在5分钟内心情值下降速率提升100%，获得心情值时降低60%。（在此期间可使心情达到非常沮丧状态）"
  },
  "厌恶犀牛": {
    "3": "附近有犀牛时心生厌恶，心情值下降6点，并在5分钟内心情值下降速率提升100%，获得心情值时降低60%。（在此期间可使心情达到非常沮丧状态）"
  },
  "厌恶犰狳蜥": {
    "3": "附近有犰狳蜥时心生厌恶，心情值下降6点，并在5分钟内心情值下降速率提升100%，获得心情值时降低60%。（在此期间可使心情达到非常沮丧状态）"
  },
  "厌恶猴子": {
    "3": "对猴子深恶痛绝，附近有猴子存在时心情值下降6点，并在5分钟内心情值下降速率提升100%，获得心情值时降低60%。（在此期间可使心情达到非常沮丧状态）"
  },
  "厌恶番茄": {
    "3": "吃到番茄时，心情值下降6点，并在5分钟内心情值下降速率提升100%，获得心情值时降低60%。（在此期间可使心情达到非常沮丧状态）"
  },
  "厌恶皮质衣物": {
    "3": "装备皮质衣物时，心情值下降6点，并在5分钟内心情值下降速率提升100%，获得心情值时降低60%。（在此期间可使心情达到非常沮丧状态）"
  },
  "厌恶石制武器": {
    "3": "不喜欢粗糙的武器，装备石制武器时，心情值下降6点，并在5分钟内心情值下降速率提升100%，获得心情值时降低60%。（在此期间可使心情达到非常沮丧状态）"
  },
  "厌恶羊驼和大羊驼": {
    "3": "羊驼和大羊驼的一切都让人难以忍受，附近有此类动物存在时心情值下降6点，并在5分钟内心情值下降速率提升100%，获得心情值时降低60%。（在此期间可使心情达到非常沮丧状态）"
  },
  "厌恶群居": {
    "3": "待在超过10人的部落时心生厌恶，心情值下降6点，并在5分钟内心情值下降速率提升100%，获得心情值时降低60%。（在此期间可使心情达到非常沮丧状态）"
  },
  "厌恶肉食": {
    "3": "吃到肉类食物时，心情值下降6点，并在5分钟内心情值下降速率提升100%，获得心情值时降低60%。（在此期间可使心情达到非常沮丧状态）"
  },
  "厌恶舒适温度": {
    "3": "对温度非常敏感，身处舒适的环境温度中时，心情值下降6点，并在5分钟内心情值下降速率提升100%，获得心情值时降低60%。（在此期间可使心情达到非常沮丧状态）"
  },
  "厌恶象龟": {
    "3": "附近有象龟时心生厌恶，心情值下降6点，并在5分钟内心情值下降速率提升100%，获得心情值时降低60%。（在此期间可使心情达到非常沮丧状态）"
  },
  "厌恶豹子": {
    "3": "刻在骨子里的恐惧，附近有豹子存在时心情值下降6点，并在5分钟内心情值下降速率提升100%，获得心情值时降低60%。（在此期间可使心情达到非常沮丧状态）"
  },
  "厌恶起床": {
    "3": "每次起床时情绪极差，心情值下降6点，并在5分钟内心情值下降速率提升100%，获得心情值时降低60%。（在此期间可使心情达到非常沮丧状态）"
  },
  "厌恶跳舞": {
    "3": "四肢不够协调十分厌恶跳舞，跳舞时心情值下降6点，并在5分钟内心情值下降速率提升100%，获得心情值时降低60%。（在此期间可使心情达到非常沮丧状态）"
  },
  "厌恶酱熟肉": {
    "3": "吃到酱熟肉时，心情值下降6点，并在5分钟内心情值下降速率提升100%，获得心情值时降低60%。（在此期间可使心情达到非常沮丧状态）"
  },
  "厌恶野猪": {
    "3": "附近有野猪时心生厌恶，心情值下降6点，并在5分钟内心情值下降速率提升100%，获得心情值时降低60%。（在此期间可使心情达到非常沮丧状态）"
  },
  "厌恶长角牛": {
    "3": "附近有长角牛时心生厌恶，心情值下降6点，并在5分钟内心情值下降速率提升100%，获得心情值时降低60%。（在此期间可使心情达到非常沮丧状态）"
  },
  "厌恶青铜护甲": {
    "3": "装备青铜护甲时，心情值下降6点，并在5分钟内心情值下降速率提升100%，获得心情值时降低60%。（在此期间可使心情达到非常沮丧状态）"
  },
  "厌恶青铜武器": {
    "3": "装备青铜武器时，心情值下降6点，并在5分钟内心情值下降速率提升100%，获得心情值时降低60%。（在此期间可使心情达到非常沮丧状态）"
  },
  "厌恶食人鱼": {
    "3": "附近有食人鱼时心生厌恶，心情值下降6点，并在5分钟内心情值下降速率提升100%，获得心情值时降低60%。（在此期间可使心情达到非常沮丧状态）"
  },
  "厌恶饮酒": {
    "3": "对酒水的气味异常敏感，喝酒时心情值下降6点，并在5分钟内心情值下降速率提升100%，获得心情值时降低60%。（在此期间可使心情达到非常沮丧状态）"
  },
  "厌恶驴": {
    "3": "附近有驴时心生厌恶，心情值下降6点，并在5分钟内心情值下降速率提升100%，获得心情值时降低60%。（在此期间可使心情达到非常沮丧状态）"
  },
  "厌恶骆驼": {
    "3": "附近有骆驼时心生厌恶，心情值下降6点，并在5分钟内心情值下降速率提升100%，获得心情值时降低60%。（在此期间可使心情达到非常沮丧状态）"
  },
  "厌恶骨制武器": {
    "3": "装备骨制武器时，心情值下降6点，并在5分钟内心情值下降速率提升100%，获得心情值时降低60%。（在此期间可使心情达到非常沮丧状态）"
  },
  "厌恶鸡": {
    "3": "附近有鸡时心生厌恶，心情值下降6点，并在5分钟内心情值下降速率提升100%，获得心情值时降低60%。（在此期间可使心情达到非常沮丧状态）"
  },
  "厌恶鸵鸟": {
    "3": "对鸵鸟深恶痛绝，附近有鸵鸟存在时心情值下降6点，并在5分钟内心情值下降速率提升100%，获得心情值时降低60%。（在此期间可使心情达到非常沮丧状态）"
  },
  "厌恶鹦鹉": {
    "3": "每次听到鹦鹉的声音都有想掐死它的心，附近有鹦鹉存在时心情值下降6点，并在5分钟内心情值下降速率提升100%，获得心情值时降低60%。（在此期间可使心情达到非常沮丧状态）"
  },
  "友谊之焰": {
    "1": "与好友一起燃烧生命何尝不是一件美事，身体被点燃时会将火焰传递给1米范围内的友方。",
    "2": "与好友一起燃烧生命何尝不是一件美事，身体被点燃时会将火焰传递给2米范围内的友方。",
    "3": "与好友一起燃烧生命何尝不是一件美事，身体被点燃时会将火焰传递给3米范围内的友方。"
  },
  "双刀减伤": {
    "1": "使用双刀威胁减弱，使用双刀类武器造成的伤害降低10%。",
    "2": "使用双刀威胁减弱，使用双刀类武器造成的伤害降低15%。",
    "3": "使用双刀威胁减弱，使用双刀类武器造成的伤害降低20%。"
  },
  "双刀增伤": {
    "1": "使用双刀威力更强，双刀类武器造成的伤害提升3%。",
    "2": "使用双刀威力更强，双刀类武器造成的伤害提升6%。",
    "3": "使用双刀威力更强，双刀类武器造成的伤害提升9%。"
  },
  "反击时刻": {
    "2": "防御敌人攻击后自身获得一层伤害提高5%的效果，持续6s。（冷却时间15s）"
  },
  "后发制人": {
    "1": "【毒牙专属】阅读进攻伺机而动，成功闪避敌人2次攻击后（每次间隔不超过6s），接下来3s内的攻击可以无视敌人防御力。",
    "2": "【毒牙专属】阅读进攻伺机而动，成功闪避敌人2次攻击后（每次间隔不超过6s），接下来5s内的攻击可以无视敌人防御力。",
    "3": "【毒牙专属】阅读进攻伺机而动，成功闪避敌人2次攻击后（每次间隔不超过6s），接下来7s内的攻击可以无视敌人防御力。"
  },
  "喘息之机": {
    "1": "首次受到武器攻击后，该伤害将在5秒内恢复。若在恢复期间再次受到武器攻击，则立即对自身造成与首次武器攻击相等的伤害，并终止恢复效果。（冷却时间10秒）",
    "2": "首次受到武器攻击后，该伤害将在4秒内恢复。若在恢复期间再次受到武器攻击，则立即对自身造成与首次武器攻击相等的伤害，并终止恢复效果。（冷却时间8秒）",
    "3": "首次受到武器攻击后，该伤害将在3秒内恢复。若在恢复期间再次受到武器攻击，则立即对自身造成与首次武器攻击相等的伤害，并终止恢复效果。（冷却时间5秒）"
  },
  "喜好下雨": {
    "1": "对雨天情有独钟，下雨时获得20点心情值，并在15分钟内心情值下降速率降低30%，获得心情值时提升75%。",
    "2": "对雨天情有独钟，下雨时获得40点心情值，并在15分钟内心情值下降速率降低50%，获得心情值时提升100%。"
  },
  "喜好下雪": {
    "1": "对雪天情有独钟，下雪时获得20点心情值，并在15分钟内心情值下降速率降低30%，获得心情值时提升75%。",
    "2": "对雪天情有独钟，下雪时获得40点心情值，并在15分钟内心情值下降速率降低50%，获得心情值时提升100%。"
  },
  "喜好主食": {
    "1": "每当吃到能填饱肚子的食物便感到身心舒畅，获得20点心情值，并在15分钟内心情值下降速率降低30%，获得心情值时提升75%。",
    "2": "每当吃到能填饱肚子的食物便感到身心舒畅，获得40点心情值，并在15分钟内心情值下降速率降低50%，获得心情值时提升100%。"
  },
  "喜好传奇首领": {
    "1": "该蛮人追随的首领是红色品质时令其倍感心安，获得20点心情值，并在15分钟内心情值下降速率降低30%，获得心情值时提升75%。",
    "2": "该蛮人追随的首领是红色品质时令其倍感心安，获得40点心情值，并在15分钟内心情值下降速率降低50%，获得心情值时提升100%。"
  },
  "喜好傍水": {
    "1": "喜欢生活在有水的地方，生活区域附近有水域时，获得20点心情值，并在15分钟内心情值下降速率降低30%，获得心情值时提升75%。",
    "2": "喜欢生活在有水的地方，生活区域附近有水域时，获得40点心情值，并在15分钟内心情值下降速率降低50%，获得心情值时提升100%。"
  },
  "喜好动物": {
    "1": "附近存在任何动物时都会感到愉快，每隔一段时间获得20点心情值，并在15分钟内心情值下降速率降低30%，获得心情值时提升75%。",
    "2": "附近存在任何动物时都会感到愉快，每隔一段时间获得40点心情值，并在15分钟内心情值下降速率降低50%，获得心情值时提升100%。"
  },
  "喜好喝酒": {
    "1": "喜欢饮酒，喝酒时身心舒畅，获得20点心情值，并在15分钟内心情值下降速率降低30%，获得心情值时提升75%。",
    "2": "喜欢饮酒，喝酒时身心舒畅，获得40点心情值，并在15分钟内心情值下降速率降低50%，获得心情值时提升100%。"
  },
  "喜好寒冷": {
    "1": "感到寒冷时产生特殊的生理反应，获得20点心情值，并在15分钟内心情值下降速率降低30%，获得心情值时提升75%。",
    "2": "感到寒冷时产生特殊的生理反应，获得40点心情值，并在15分钟内心情值下降速率降低50%，获得心情值时提升100%。"
  },
  "喜好巨象": {
    "1": "附近有巨象时会感到愉快，每隔一段时间获得20点心情值，并在15分钟内心情值下降速率降低30%，获得心情值时提升75%。",
    "2": "附近有巨象时会感到愉快，每隔一段时间获得40点心情值，并在15分钟内心情值下降速率降低50%，获得心情值时提升100%。"
  },
  "喜好布制衣物": {
    "1": "喜欢布质衣物的触感，穿戴布质装备时身心舒畅，获得20点心情值，并在15分钟内心情值下降速率降低30%，获得心情值时提升75%。",
    "2": "喜欢布质衣物的触感，穿戴布质装备时身心舒畅，获得40点心情值，并在15分钟内心情值下降速率降低50%，获得心情值时提升100%。"
  },
  "喜好排泄": {
    "1": "排泄使人愉快，排泄时会获得20点心情值，并在15分钟内心情值下降速率降低30%，获得心情值时提升75%。",
    "2": "排泄使人愉快，排泄时会获得40点心情值，并在15分钟内心情值下降速率降低50%，获得心情值时提升100%。"
  },
  "喜好晴天": {
    "1": "晴朗的天气让人身心舒畅，晴天时获得20点心情值，并在15分钟内心情值下降速率降低30%，获得心情值时提升75%。",
    "2": "晴朗的天气让人身心舒畅，晴天时获得40点心情值，并在15分钟内心情值下降速率降低50%，获得心情值时提升100%。"
  },
  "喜好杰出首领": {
    "1": "该蛮人追随的首领是紫色及以上品质时，获得20点心情值，并在15分钟内心情值下降速率降低30%，获得心情值时提升75%。",
    "2": "该蛮人追随的首领是紫色及以上品质时，获得40点心情值，并在15分钟内心情值下降速率降低50%，获得心情值时提升100%。"
  },
  "喜好果蔬": {
    "1": "喜欢吃水果蔬菜，吃到合适的食物时身心舒畅，获得20点心情值，并在15分钟内心情值下降速率降低30%，获得心情值时提升75%。",
    "2": "喜欢吃水果蔬菜，吃到合适的食物时身心舒畅，获得40点心情值，并在15分钟内心情值下降速率降低50%，获得心情值时提升100%。"
  },
  "喜好河马": {
    "1": "附近有河马时会感到愉快，每隔一段时间获得20点心情值，并在15分钟内心情值下降速率降低30%，获得心情值时提升75%。",
    "2": "附近有河马时会感到愉快，每隔一段时间获得40点心情值，并在15分钟内心情值下降速率降低50%，获得心情值时提升100%。"
  },
  "喜好洗澡": {
    "1": "洗澡使人心情愉悦，获得20点心情值，并在15分钟内心情值下降速率降低30%，获得心情值时提升75%。",
    "2": "洗澡使人心情愉悦，获得40点心情值，并在15分钟内心情值下降速率降低50%，获得心情值时提升100%。"
  },
  "喜好清寒": {
    "1": "感到清寒时产生特殊的生理反应，获得20点心情值，并在15分钟内心情值下降速率降低30%，获得心情值时提升75%。",
    "2": "感到清寒时产生特殊的生理反应，获得40点心情值，并在15分钟内心情值下降速率降低50%，获得心情值时提升100%。"
  },
  "喜好温热": {
    "1": "感到温热时产生特殊的生理反应，获得20点心情值，并在15分钟内心情值下降速率降低30%，获得心情值时提升75%。",
    "2": "感到温热时产生特殊的生理反应，获得40点心情值，并在15分钟内心情值下降速率降低50%，获得心情值时提升100%。"
  },
  "喜好火烈鸟": {
    "1": "附近有火烈鸟时会感到愉快，每隔一段时间获得20点心情值，并在15分钟内心情值下降速率降低30%，获得心情值时提升75%。",
    "2": "附近有火烈鸟时会感到愉快，每隔一段时间获得40点心情值，并在15分钟内心情值下降速率降低50%，获得心情值时提升100%。"
  },
  "喜好炎热": {
    "1": "感到炎热时产生特殊的生理反应，获得20点心情值，并在15分钟内心情值下降速率降低30%，获得心情值时提升75%。",
    "2": "感到炎热时产生特殊的生理反应，获得40点心情值，并在15分钟内心情值下降速率降低50%，获得心情值时提升100%。"
  },
  "喜好烟草": {
    "1": "喜欢烟草的味道，抽烟时身心舒畅，获得20点心情值，并在15分钟内心情值下降速率降低30%，获得心情值时提升75%。",
    "2": "喜欢烟草的味道，抽烟时身心舒畅，获得40点心情值，并在15分钟内心情值下降速率降低50%，获得心情值时提升100%。"
  },
  "喜好犀牛": {
    "1": "附近有犀牛时会感到愉快，每隔一段时间获得20点心情值，并在15分钟内心情值下降速率降低30%，获得心情值时提升75%。",
    "2": "附近有犀牛时会感到愉快，每隔一段时间获得40点心情值，并在15分钟内心情值下降速率降低50%，获得心情值时提升100%。"
  },
  "喜好犰狳蜥": {
    "1": "附近有犰狳蜥时会感到愉快，每隔一段时间获得20点心情值，并在15分钟内心情值下降速率降低30%，获得心情值时提升75%。",
    "2": "附近有犰狳蜥时会感到愉快，每隔一段时间获得40点心情值，并在15分钟内心情值下降速率降低50%，获得心情值时提升100%。"
  },
  "喜好番茄": {
    "1": "喜欢吃番茄，吃到番茄时身心舒畅，获得20点心情值，并在15分钟内心情值下降速率降低30%，获得心情值时提升75%。",
    "2": "喜欢吃番茄，吃到番茄时身心舒畅，获得40点心情值，并在15分钟内心情值下降速率降低50%，获得心情值时提升100%。"
  },
  "喜好皮质衣物": {
    "1": "喜欢皮质衣物的触感，穿戴皮质装备时身心舒畅，获得20点心情值，并在15分钟内心情值下降速率降低30%，获得心情值时提升75%。",
    "2": "喜欢皮质衣物的触感，穿戴皮质装备时身心舒畅，获得40点心情值，并在15分钟内心情值下降速率降低50%，获得心情值时提升100%。"
  },
  "喜好石制武器": {
    "1": "喜好石制武器，装备石制武器时身心舒畅，获得20点心情值，并在15分钟内心情值下降速率降低30%，获得心情值时提升75%。",
    "2": "喜好石制武器，装备石制武器时身心舒畅，获得40点心情值，并在15分钟内心情值下降速率降低50%，获得心情值时提升100%。"
  },
  "喜好群居": {
    "1": "喜欢在人多的地方生活，部落人数超过10人时身心舒畅，获得20点心情值，并在15分钟内心情值下降速率降低30%，获得心情值时提升75%。",
    "2": "喜欢在人多的地方生活，部落人数超过10人时身心舒畅，获得40点心情值，并在15分钟内心情值下降速率降低50%，获得心情值时提升100%。"
  },
  "喜好肉食": {
    "1": "喜欢吃肉，吃到肉食身心舒畅，获得20点心情值，并在15分钟内心情值下降速率降低30%，获得心情值时提升75%。",
    "2": "喜欢吃肉，吃到肉食身心舒畅，获得40点心情值，并在15分钟内心情值下降速率降低50%，获得心情值时提升100%。"
  },
  "喜好舒适温度": {
    "1": "处在舒适温度下时身心舒畅，获得20点心情值，并在15分钟内心情值下降速率降低30%，获得心情值时提升75%。",
    "2": "处在舒适温度下时身心舒畅，获得40点心情值，并在15分钟内心情值下降速率降低50%，获得心情值时提升100%。"
  },
  "喜好被鞭打": {
    "1": "被鞭打时产生快感3次鞭打可获得满层效果，获得20点心情，并在15分钟内心情值下降速率降低30%，获得心情值时提升75%。",
    "2": "被鞭打时产生快感2次鞭打可获得满层效果，获得40点心情值，并在15分钟内心情值下降速率降低50%，获得心情值时提升100%。"
  },
  "喜好象龟": {
    "1": "附近有象龟时会感到愉快，每隔一段时间获得20点心情值，并在15分钟内心情值下降速率降低30%，获得心情值时提升75%。",
    "2": "附近有象龟时会感到愉快，每隔一段时间获得40点心情值，并在15分钟内心情值下降速率降低50%，获得心情值时提升100%。"
  },
  "喜好跳舞": {
    "1": "跳舞似乎能忘记烦恼，跳舞时获得20点心情值，并在15分钟内心情值下降速率降低30%，获得心情值时提升75%。",
    "2": "跳舞似乎能忘记烦恼，跳舞时获得40点心情值，并在15分钟内心情值下降速率降低50%，获得心情值时提升100%。"
  },
  "喜好躺平": {
    "1": "睡眠对其尤为重要，每次得到休息时身心舒畅，获得20点心情值，并在15分钟内心情值下降速率降低30%，获得心情值时提升75%。",
    "2": "睡眠对其尤为重要，每次得到休息时身心舒畅，获得40点心情值，并在15分钟内心情值下降速率降低50%，获得心情值时提升100%。"
  },
  "喜好酱熟肉": {
    "1": "喜欢酱熟肉，吃到酱熟肉时身心舒畅，获得20点心情值，并在15分钟内心情值下降速率降低30%，获得心情值时提升75%。",
    "2": "喜欢酱熟肉，吃到酱熟肉时身心舒畅，获得40点心情值，并在15分钟内心情值下降速率降低50%，获得心情值时提升100%。"
  },
  "喜好野猪": {
    "1": "附近有野猪时会感到愉快，每隔一段时间会获得20点心情值，并在15分钟内心情值下降速率降低30%，获得心情值时提升75%。",
    "2": "附近有野猪时会感到愉快，每隔一段时间获得40点心情值，并在15分钟内心情值下降速率降低50%，获得心情值时提升100%。"
  },
  "喜好长角牛": {
    "1": "附近有长角牛时会感到愉快，每隔一段时间获得20点心情值，并在15分钟内心情值下降速率降低30%，获得心情值时提升75%。",
    "2": "附近有长角牛时会感到愉快，每隔一段时间获得40点心情值，并在15分钟内心情值下降速率降低50%，获得心情值时提升100%。"
  },
  "喜好青铜护甲": {
    "1": "喜欢青铜护甲带来的安全感，穿戴青铜护甲时身心舒畅，获得20点心情值，并在15分钟内心情值下降速率降低30%，获得心情值时提升75%。",
    "2": "喜欢青铜护甲带来的安全感，穿戴青铜护甲时身心舒畅，获得40点心情值，并在15分钟内心情值下降速率降低50%，获得心情值时提升100%。"
  },
  "喜好青铜武器": {
    "1": "喜好青铜武器，装备青铜武器时身心舒畅，获得20点心情值，并在15分钟内心情值下降速率降低30%，获得心情值时提升75%。",
    "2": "喜好青铜武器，装备青铜武器时身心舒畅，获得40点心情值，并在15分钟内心情值下降速率降低50%，获得心情值时提升100%。"
  },
  "喜好鞭打": {
    "1": "鞭打他人时产生快感3次鞭打可获得满层效果，获得20点心情，并在15分钟内心情值下降速率降低30%，获得心情值时提升75%，",
    "2": "鞭打他人时产生快感2次鞭打可获得满层效果，获得40点心情值，并在15分钟内心情值下降速率降低50%，获得心情值时提升100%。"
  },
  "喜好食人鱼": {
    "1": "附近有食人鱼时会感到愉快，每隔一段时间获得20点心情值，并在15分钟内心情值下降速率降低30%，获得心情值时提升75%。",
    "2": "附近有食人鱼时会感到愉快，每隔一段时间获得40点心情值，并在15分钟内心情值下降速率降低50%，获得心情值时提升100%。"
  },
  "喜好驴": {
    "1": "附近有驴时会感到愉快，每隔一段时间获得20点心情值，并在15分钟内心情值下降速率降低30%，获得心情值时提升75%。",
    "2": "附近有驴时会感到愉快，每隔一段时间获得40点心情值，并在15分钟内心情值下降速率降低50%，获得心情值时提升100%。"
  },
  "喜好骨制武器": {
    "1": "喜好骨制武器，装备骨制武器时身心舒畅，获得20点心情值，并在15分钟内心情值下降速率降低30%，获得心情值时提升75%。",
    "2": "喜好骨制武器，装备骨制武器时身心舒畅，获得40点心情值，并在15分钟内心情值下降速率降低50%，获得心情值时提升100%。"
  },
  "喜好鸡": {
    "1": "附近有鸡时会感到愉快，每隔一段时间获得20点心情值，并在15分钟内心情值下降速率降低30%，获得心情值时提升75%。",
    "2": "附近有鸡时会感到愉快，每隔一段时间获得40点心情值，并在15分钟内心情值下降速率降低50%，获得心情值时提升100%。"
  },
  "喜欢猴子": {
    "1": "附近有猴子存在时，每隔一段时间会获得20点心情值，并在15分钟内心情值下降速率降低30%，获得心情值时提升75%。",
    "2": "附近有猴子存在时，每隔一段时间会获得40点心情值，并在15分钟内心情值下降速率降低50%，获得心情值时提升100%。"
  },
  "喜欢羊驼和大羊驼": {
    "1": "附近有羊驼或大羊驼存在时会感到愉快，每隔一段时间会获得20点心情值，并在15分钟内心情值下降速率降低30%，获得心情值时提升75%。",
    "2": "附近有羊驼或大羊驼存在时会感到愉快，每隔一段时间会获得40点心情值，并在15分钟内心情值下降速率降低50%，获得心情值时提升100%。"
  },
  "喜欢豹子": {
    "1": "附近有豹子存在时会感到愉快，每隔一段时间会获得20点心情值，并在15分钟内心情值下降速率降低30%，获得心情值时提升75%。",
    "2": "附近有豹子存在时会感到愉快，每隔一段时间会获得40点心情值，并在15分钟内心情值下降速率降低50%，获得心情值时提升100%。"
  },
  "喜欢鸵鸟": {
    "1": "附近有鸵鸟存在时会感到愉快，每隔一段时间会获得20点心情值，并在15分钟内心情值下降速率降低30%，获得心情值时提升75%。",
    "2": "附近有鸵鸟存在时会感到愉快，每隔一段时间会获得40点心情值，并在15分钟内心情值下降速率降低50%，获得心情值时提升100%。"
  },
  "喜欢鹦鹉": {
    "1": "附近有鹦鹉存在时会感到愉快，每隔一段时间会获得20点心情值，并在15分钟内心情值下降速率降低30%，获得心情值时提升75%。",
    "2": "附近有鹦鹉存在时会感到愉快，每隔一段时间会获得40点心情值，并在15分钟内心情值下降速率降低50%，获得心情值时提升100%。"
  },
  "喜爱骆驼": {
    "1": "附近有骆驼时会感到愉快，每隔一段时间获得20点心情值，并在15分钟内心情值下降速率降低30%，获得心情值时提升75%。",
    "2": "附近有骆驼时会感到愉快，每隔一段时间获得40点心情值，并在15分钟内心情值下降速率降低50%，获得心情值时提升100%。"
  },
  "嗜好下雨": {
    "3": "对雨天情有独钟，下雨时获得60点心情值，并在15分钟内心情值下降速率降低70%，获得心情值时提升125%。（在此期间可使心情达到非常愉快状态）"
  },
  "嗜好下雪": {
    "3": "对雪天情有独钟，下雪时获得60点心情值，并在15分钟内心情值下降速率降低70%，获得心情值时提升125%。（在此期间可使心情达到非常愉快状态）"
  },
  "嗜好主食": {
    "3": "每当吃到主食类型的食物时十分满足，获得60点心情值，并在15分钟内心情值下降速率降低70%，获得心情值时提升125%。（在此期间可使心情达到非常愉快状态）"
  },
  "嗜好传奇首领": {
    "3": "该蛮人追随的首领是红色品质时令其心悦诚服，获得60点心情值，并在15分钟内心情值下降速率降低70%，获得心情值时提升125%。（在此期间可使心情达到非常愉快状态）"
  },
  "嗜好傍水": {
    "3": "对水域有种特殊的依赖，生活区域附近有水域时，获得60点心情值，并在15分钟内心情值下降速率降低70%，获得心情值时提升125%。（在此期间可使心情达到非常愉快状态）"
  },
  "嗜好喝酒": {
    "3": "嗜酒如命，喝到酒水时十分满足，获得60点心情值，并在15分钟内心情值下降速率降低70%，获得心情值时提升125%。（在此期间可使心情达到非常愉快状态）"
  },
  "嗜好寒冷": {
    "3": "非常特殊的癖好，感到寒冷时身体莫名兴奋，获得60点心情值，并在15分钟内心情值下降速率降低70%，获得心情值时提升125%。（在此期间可使心情达到非常愉快状态）"
  },
  "嗜好布制衣物": {
    "3": "布衣狂热者，穿戴布质装备时十分满足，获得60点心情值，并在15分钟内心情值下降速率降低70%，获得心情值时提升125%。（在此期间可使心情达到非常愉快状态）"
  },
  "嗜好排泄": {
    "3": "特殊癖好每次排泄时都快感倍增，排泄时会获得60点心情值，并在15分钟内心情值下降速率降低70%，获得心情值时提升125%。（在此期间可使心情达到非常愉快状态）"
  },
  "嗜好晴天": {
    "3": "晴朗的天气让人身心舒畅，晴天时获得60点心情值，并在15分钟内心情值下降速率降低70%，获得心情值时提升125%。（在此期间可使心情达到非常愉快状态）"
  },
  "嗜好杰出首领": {
    "3": "该蛮人追随的首领是紫色及以上品质时令其心悦诚服，获得60点心情值，并在15分钟内心情值下降速率降低70%，获得心情值时提升125%。（在此期间可使心情达到非常愉快状态）"
  },
  "嗜好果蔬": {
    "3": "果蔬狂热者，吃到果蔬时非常满足，获得60点心情值，并在15分钟内心情值下降速率降低70%，获得心情值时提升125%。（在此期间可使心情达到非常愉快状态）"
  },
  "嗜好洗澡": {
    "3": "洗澡时倍感幸福，获得60点心情值，并在15分钟内心情值下降速率降低70%，获得心情值时提升125%。（在此期间可使心情达到非常愉快状态）"
  },
  "嗜好清寒": {
    "3": "非常特殊的癖好感到清寒时身体莫名兴奋，获得60点心情值，并在15分钟内心情值下降速率降低70%，获得心情值时提升125%。（在此期间可使心情达到非常愉快状态）"
  },
  "嗜好温热": {
    "3": "非常特殊的癖好，感到温热时身体莫名兴奋，获得60点心情值，并在15分钟内心情值下降速率降低70%，获得心情值时提升125%。（在此期间可使心情达到非常愉快状态）"
  },
  "嗜好炎热": {
    "3": "非常特殊的癖好，感到炎热时身体莫名兴奋，获得60点心情值，并在15分钟内心情值下降速率降低70%，获得心情值时提升125%。（在此期间可使心情达到非常愉快状态）"
  },
  "嗜好烟草": {
    "3": "烟草狂热者，抽到烟草时十分满足，获得60点心情值，并在15分钟内心情值下降速率降低70%，获得心情值时提升125%。（在此期间可使心情达到非常愉快状态）"
  },
  "嗜好番茄": {
    "3": "番茄狂热者，吃到番茄时十分满足，获得60点心情值，并在15分钟内心情值下降速率降低70%，获得心情值时提升125%。（在此期间可使心情达到非常愉快状态）"
  },
  "嗜好皮质衣物": {
    "3": "皮衣狂热者，穿戴皮质装备时十分满足，获得60点心情值，并在15分钟内心情值下降速率降低70%，获得心情值时提升125%。（在此期间可使心情达到非常愉快状态）"
  },
  "嗜好石制武器": {
    "3": "石制武器狂热者，装备石制武器时心满意足，获得60点心情值，并在15分钟内心情值下降速率降低70%，获得心情值时提升125%。（在此期间可使心情达到非常愉快状态）"
  },
  "嗜好群居": {
    "3": "钟爱群居，部落人数超过10人时会产生极大的安全感，获得60点心情值，并在15分钟内心情值下降速率降低70%，获得心情值时提升125%。（在此期间可使心情达到非常愉快状态）"
  },
  "嗜好肉食": {
    "3": "肉食狂热，吃到肉食十分满足，获得60点心情值，并在15分钟内心情值下降速率降低70%，获得心情值时提升125%。（在此期间可使心情达到非常愉快状态）"
  },
  "嗜好舒适温度": {
    "3": "钟爱令人舒适的温度身处其中时，获得60点心情值，并在15分钟内心情值下降速率降低70%，获得心情值时提升125%。（在此期间可使心情达到非常愉快状态）"
  },
  "嗜好被鞭打": {
    "3": "被鞭打时产生强烈快感1次鞭打可获得满层效果，获得60点心情值，并在15分钟内心情值下降速率降低70%，获得心情值时提升125%。（在此期间可使心情达到非常愉快状态）"
  },
  "嗜好跳舞": {
    "3": "随着节奏舞动时才是真正的自由，跳舞时获得60点心情值，并在15分钟内心情值下降速率降低70%，获得心情值时提升125%。（在此期间可使心情达到非常愉快状态）"
  },
  "嗜好躺平": {
    "3": "酷爱睡眠，每次休息时倍感满足，获得60点心情值，并在15分钟内心情值下降速率降低70%，获得心情值时提升125%。（在此期间可使心情达到非常愉快状态）"
  },
  "嗜好酱熟肉": {
    "3": "钟爱酱熟肉，吃到酱熟肉时十分满足，获得60点心情值，并在15分钟内心情值下降速率降低70%，获得心情值时提升125%。（在此期间可使心情达到非常愉快状态）"
  },
  "嗜好青铜护甲": {
    "3": "钟爱青铜护甲，穿戴青铜护甲时心满意足，获得60点心情值，并在15分钟内心情值下降速率降低70%，获得心情值时提升125%。（在此期间可使心情达到非常愉快状态）"
  },
  "嗜好青铜武器": {
    "3": "青铜武器狂热者，装备青铜武器时心满意足，获得60点心情值，并在15分钟内心情值下降速率降低70%，获得心情值时提升125%。（在此期间可使心情达到非常愉快状态）"
  },
  "嗜好鞭打": {
    "3": "鞭打他人时产生强烈快感1次鞭打可获得满层效果，获得60点心情值，并在15分钟内心情值下降速率降低70%，获得心情值时提升125%。（在此期间可使心情达到非常愉快状态）"
  },
  "嗜好骨制武器": {
    "3": "骨制武器狂热者，装备骨制武器时十分满足，获得60点心情值，并在15分钟内心情值下降速率降低70%，获得心情值时提升125%。（在此期间可使心情达到非常愉快状态）"
  },
  "回光反击": {
    "1": "在生命值回满或者从濒死回到正常状态后的2秒内，受到来自5米以内的攻击，返还100%伤害给攻击者。（冷却时间30秒）",
    "2": "在生命值回满或者从濒死回到正常状态后的4秒内，受到来自5米以内的攻击，返还100%伤害给攻击者。（冷却时间30秒）",
    "3": "在生命值回满或者从濒死回到正常状态后的6秒内，受到来自5米以内的攻击，返还100%伤害给攻击者。（冷却时间30秒）"
  },
  "回光返照": {
    "1": "生命力顽强，生命值低于10%时会在5s内恢复20%生命值。(冷却时间40s)",
    "2": "生命力顽强，生命值低于20%时会在5s内恢复20%生命值。(冷却时间40s)",
    "3": "生命力顽强，生命值低于30%时会在5s内恢复20%生命值。(冷却时间40s)"
  },
  "坚定不移": {
    "1": "沉着冷静临危不乱，6秒内没有任何移动时即会获得一层攻击力提升1%，攻击速度提升2%，暴击提升2%，暴击伤害提升2%，但此阶段自身受到的伤害会少量提升，至多叠加5层，移动后即会移除所有效果。",
    "2": "沉着冷静临危不乱，6秒内没有任何移动时即会获得一层攻击力提升1.5%，攻击速度提升2%，暴击提升2%，暴击伤害提升3%，但此阶段自身受到的伤害会少量提升，至多叠加5层，移动后即会移除所有效果。",
    "3": "沉着冷静临危不乱，6秒内没有任何移动时即会获得一层攻击力提升2%，攻击速度提升2%，暴击提升3%，暴击伤害提升4%，但此阶段自身受到的伤害会少量提升，至多叠加5层，移动后即会移除所有效果。"
  },
  "垂死挣扎": {
    "2": "生命值低于15%时会在5s内恢复15%的生命值。（冷却时间35s）"
  },
  "增伤祈佑": {
    "1": "攻击命中目标时有5%概率触发，接下来对目标造成的10次武器伤害将锁定为近期内的最高伤害值，持续8秒。（冷却时间30秒）",
    "2": "攻击命中目标时有10%概率触发，使接下来对目标造成的10次武器伤害将锁定为近期内的最高伤害值，持续10秒。（冷却时间30秒）",
    "3": "攻击命中目标时有15%概率触发，使接下来对目标造成的10次武器伤害将锁定为近期内的最高伤害值，持续12秒。（冷却时间30秒）"
  },
  "增伤窃取": {
    "1": "【荒狼专属】攻击命中目标时有5%概率触发，窃取目标10%的伤害提升，转化为自身的提升，持续12秒，至多叠加5层。",
    "2": "【荒狼专属】攻击命中目标时有10%概率触发，窃取目标10%的伤害提升，转化为自身的提升，持续12秒，至多叠加5层。",
    "3": "【荒狼专属】攻击命中目标时有15%概率触发，窃取目标10%的伤害提升，转化为自身的提升，持续12秒，至多叠加5层。"
  },
  "处决威慑": {
    "1": "处决目标时可以削弱10米范围内的敌人，使其陷入懦弱状态攻击力、暴击下降10%，攻击速度下降5%，持续15秒。",
    "2": "处决目标时可以削弱10米范围内的敌人，使其陷入懦弱状态攻击力、暴击下降15%，攻击速度下降10%，持续15秒。",
    "3": "处决目标时可以削弱10米范围内的敌人，使其陷入懦弱状态攻击力、暴击下降20%，攻击速度下降15%，持续15秒。"
  },
  "复仇之怒": {
    "1": "化悲愤为力量，周围10米内有友方濒死或死亡时会被彻底激怒，攻击力提升10%，防御力提升15%，攻击速度提升5%，移动速度提升5%，每秒恢复体力10点，持续20秒。（冷却时间50s）",
    "2": "化悲愤为力量，周围10米内有友方濒死或死亡时会被彻底激怒，攻击力提升15%，防御力提升20%，攻击速度提升7.5%，移动速度提升10%，每秒恢复体力15点，持续20秒。（冷却时间50s）",
    "3": "化悲愤为力量，周围10米内有友方濒死或死亡时会被彻底激怒，攻击力提升20%，防御力提升25%，攻击速度提升10%，移动速度提升15%，每秒恢复体力20点，持续20秒。（冷却时间50s）"
  },
  "多重射击": {
    "3": "【猎手专属】掌握弓类专精技能（射击技巧）的多重发射能力，每次使用此类技能时都会射出多支箭矢。"
  },
  "多重投掷": {
    "1": "使用投掷物时有10%的概率额外扔出数个。",
    "2": "使用投掷物时有15%的概率额外扔出数个。",
    "3": "使用投掷物时有20%的概率额外扔出数个。"
  },
  "夜行者": {
    "3": "习惯黑夜融入黑夜成为黑夜，在黑夜中行动时移动速度提升10%，暴击提升5%。"
  },
  "大腿应激": {
    "1": "大腿受到攻击时有20%概率产生应激反应，接下来受到的伤害降低20%，持续5秒。(冷却时间12s)",
    "2": "大腿受到攻击时有20%概率产生应激反应，接下来受到的伤害降低30%，持续5秒。(冷却时间12s)",
    "3": "大腿受到攻击时有20%概率产生应激反应，接下来受到的伤害降低50%，持续5秒。(冷却时间12s)"
  },
  "大锤减伤": {
    "1": "使用大锤威胁减弱，使用锤类武器造成的伤害降低10%。",
    "2": "使用大锤威胁减弱，使用锤类武器造成的伤害降低15%。",
    "3": "使用大锤威胁减弱，使用锤类武器造成的伤害降低20%。"
  },
  "大锤增伤": {
    "1": "使用大锤威力更强，锤类武器造成的伤害提升3%。",
    "2": "使用大锤威力更强，锤类武器造成的伤害提升6%。",
    "3": "使用大锤威力更强，锤类武器造成的伤害提升9%。"
  },
  "天生反骨": {
    "3": "自命不凡内心从未认同过其他人，认同度降低速度提升200%，认同度过低时会携带一部分部落资产叛逃，当认同度降至400以下时暴露真我，在目标背后进行攻击时造成的伤害提升15%。"
  },
  "天生苦力": {
    "3": "命运凄苦天生苦力，伐木、采矿的熟练度成长速度提升50%。"
  },
  "天生霉运": {
    "1": "被霉运之神眷顾，使所有概率触发的天赋，触发概率降低10%。",
    "2": "被霉运之神眷顾，使所有概率触发的天赋，触发概率降低15%。",
    "3": "被霉运之神眷顾，使所有概率触发的天赋，触发概率降低20%。"
  },
  "天赋异禀": {
    "1": "众神赋予的特殊运气，使所有概率触发的天赋概率提升10%。",
    "2": "众神赋予的特殊运气，使所有概率触发的天赋概率提升15%。",
    "3": "众神赋予的特殊运气，使所有概率触发的天赋概率提升20%。"
  },
  "头部应激": {
    "1": "头部受到攻击时有20%概率产生应激反应，接下来受到的伤害降低20%，持续5秒。(冷却时间12s)",
    "2": "头部受到攻击时有20%概率产生应激反应，接下来受到的伤害降低30%，持续5秒。(冷却时间12s)",
    "3": "头部受到攻击时有20%概率产生应激反应，接下来受到的伤害降低50%，持续5秒。(冷却时间12s)"
  },
  "头部破坏": {
    "1": "精通头部结构，攻击到目标头部时，有20%概率伤害提升10%。",
    "2": "精通头部结构，攻击到目标头部时，有20%概率伤害提升15%。",
    "3": "精通头部结构，攻击到目标头部时，有20%概率伤害提升25%。"
  },
  "夺势": {
    "1": "弹反敌人攻击时，若敌人当前的攻防相关属性高于自身，则强化自身较低的部分，基于敌人实力至多提升20%，持续12秒。（冷却时间60秒）",
    "2": "弹反敌人攻击时，若敌人当前的攻防相关属性高于自身，则强化自身较低的部分，基于敌人实力至多提升20%，持续12秒。（冷却时间45秒）",
    "3": "弹反敌人攻击时，若敌人当前的攻防相关属性高于自身，则强化自身较低的部分，基于敌人实力至多提升20%，持续12秒。（冷却时间30秒）"
  },
  "夺心者": {
    "3": "作为部落刽子手时恶行昭著名声在外，对躯干部位的伤害永久提升12%。"
  },
  "奋起反击": {
    "1": "身体每个关节对敌人都是威胁，身体受到来自5米以内的攻击时（头部除外），返还10%伤害给攻击者。",
    "2": "身体每个关节对敌人都是威胁，身体受到来自5米以内的攻击时（头部除外），返还15%伤害给攻击者。",
    "3": "身体每个关节对敌人都是威胁，身体受到来自5米以内的攻击时（头部除外），返还20%伤害给攻击者。"
  },
  "嫁祸": {
    "1": "【蛮角专属】受到攻击时有15%概率触发，在8秒内，能将敌人施加的持续效果转移到15米范围内其他敌人身上。（冷却时间60秒）",
    "2": "【蛮角专属】受到攻击时有15%概率触发，在10秒内，能将敌人施加的持续效果转移到15米范围内其他敌人身上。（冷却时间45秒）",
    "3": "【蛮角专属】受到攻击时有15%概率触发，在12秒内，能将敌人施加的持续效果转移到15米范围内其他敌人身上。（冷却时间30秒）"
  },
  "完美吸收": {
    "1": "在受到任何生命恢复类效果时恢复量提升20%。",
    "2": "在受到任何生命恢复类效果时恢复量提升35%。",
    "3": "在受到任何生命恢复类效果时恢复量提升50%。"
  },
  "容易口渴": {
    "1": "胃口很小只能喝一点水，最大水分降低20%。",
    "2": "胃口很小只能喝一点水，最大水分降低30%。",
    "3": "胃口很小只能喝一点水，最大水分降低40%。"
  },
  "容易饥饿": {
    "1": "胃口很小只能吃一点食物，最大饱食度降低20%。",
    "2": "胃口很小只能吃一点食物，最大饱食度降低30%。",
    "3": "胃口很小只能吃一点食物，最大饱食度降低40%。"
  },
  "射手脚步": {
    "1": "【猎手专属】掌握特殊的弓类武器移动技巧，拉弓时移动速度提升10%，持续5秒。触发加速时有5%的概率移除大多数减速效果。（冷却时间8秒）",
    "2": "【猎手专属】掌握特殊的弓类武器移动技巧，拉弓时移动速度提升15%，持续5秒。触发加速时有10%的概率移除大多数减速效果。（冷却时间8秒）",
    "3": "【猎手专属】掌握特殊的弓类武器移动技巧，拉弓时移动速度提升20%，持续5秒。触发加速时有15%的概率移除大多数减速效果。（冷却时间8秒）"
  },
  "尾部破坏": {
    "1": "熟知尾部结构，攻击到目标尾部时，有20%概率伤害提升10%。",
    "2": "熟知尾部结构，攻击到目标尾部时，有20%概率伤害提升15%。",
    "3": "熟知尾部结构，攻击到目标尾部时，有20%概率伤害提升25%。"
  },
  "屠宰能手": {
    "3": "村里最好的屠宰师傅，屠宰动物的产出提升20%。"
  },
  "屠戮狂热": {
    "1": "手刃敌人的快感无以言表，每使一名敌人濒死或死亡，自身将获得5秒霸体并且在此期间暴抗极大幅度提升。（冷却时间30s）",
    "2": "手刃敌人的快感无以言表，每使一名敌人濒死或死亡，自身将获得7.5秒霸体并且在此期间暴抗极大幅度提升。（冷却时间30s）",
    "3": "手刃敌人的快感无以言表，每使一名敌人濒死或死亡，自身将获得10秒霸体并且在此期间暴抗极大幅度提升。（冷却时间30s）"
  },
  "工具精修": {
    "1": "【匠人专属】修理工具的耐久损耗降低20%。",
    "2": "【匠人专属】修理工具的耐久损耗降低35%。",
    "3": "【匠人专属】修理工具的耐久损耗降低50%。"
  },
  "工匠制造加速": {
    "1": "【匠人专属】精通加工，完成工匠制作任务的时间缩短10%。",
    "2": "【匠人专属】精通加工，完成工匠制作任务的时间缩短20%。",
    "3": "【匠人专属】精通加工，完成工匠制作任务的时间缩短30%。"
  },
  "巧劲": {
    "1": "掌握最佳的发力方式，在进行需要消耗体力的行动时体力消耗降低10%。",
    "2": "掌握最佳的发力方式，在进行需要消耗体力的行动时体力消耗降低20%。",
    "3": "掌握最佳的发力方式，在进行需要消耗体力的行动时体力消耗降低30%。"
  },
  "巧铸防具": {
    "1": "【蛮角专属】身为匠人在制作防具时有5%的概率为其增加1条额外属性。",
    "2": "【蛮角专属】身为匠人在制作防具时有10%的概率为其增加1条额外属性。",
    "3": "【蛮角专属】身为匠人在制作防具时有10%的概率至多增加2条额外属性。"
  },
  "巨剑减伤": {
    "1": "使用巨剑威胁减弱，使用巨剑类武器造成的伤害降低10%。",
    "2": "使用巨剑威胁减弱，使用巨剑类武器造成的伤害降低15%。",
    "3": "使用巨剑威胁减弱，使用巨剑类武器造成的伤害降低20%。"
  },
  "巨剑增伤": {
    "1": "使用巨剑威力更强，巨剑类武器造成的伤害提升3%。",
    "2": "使用巨剑威力更强，巨剑类武器造成的伤害提升6%。",
    "3": "使用巨剑威力更强，巨剑类武器造成的伤害提升9%。"
  },
  "幸运者": {
    "3": "每个村里总有几个运气很好的人，我就是其中之一，稀有物品掉落概率增加20%。"
  },
  "应激加速": {
    "1": "快速逃离危险，受到攻击时有20%的概率，6s内移动速度提升15%。(冷却时间20s)",
    "2": "快速逃离危险，受到攻击时有20%的概率，6s内移动速度提升20%。(冷却时间20s)",
    "3": "快速逃离危险，受到攻击时有20%的概率，6s内移动速度提升30%。(冷却时间20s)"
  },
  "建筑制造加速": {
    "1": "熟练掌握建筑制造工艺，完成建筑制造工作的时间缩短10%。",
    "2": "熟练掌握建筑制造工艺，完成建筑制造工作的时间缩短20%。",
    "3": "熟练掌握建筑制造工艺，完成建筑制造工作的时间缩短30%。"
  },
  "弓箭减伤": {
    "1": "使用弓箭威胁减弱，使用弓武器造成的伤害降低10%。",
    "2": "使用弓箭威胁减弱，使用弓武器造成的伤害降低15%。",
    "3": "使用弓箭威胁减弱，使用弓武器造成的伤害降低20%。"
  },
  "弓箭增伤": {
    "1": "使用弓箭威力更强，弓武器造成的伤害提升3%。",
    "2": "使用弓箭威力更强，弓武器造成的伤害提升6%。",
    "3": "使用弓箭威力更强，弓武器造成的伤害提升9%。"
  },
  "弱化防御": {
    "1": "空门大开，防御力降低3%。",
    "2": "空门大开，防御力降低6%。",
    "3": "空门大开，防御力降低9%。"
  },
  "弱点强化": {
    "1": "刻意加强自己的弱点部位，被攻击到弱点部位时，部位伤害降低20%。",
    "2": "刻意加强自己的弱点部位，被攻击到弱点部位时，部位伤害降低40%。",
    "3": "刻意加强自己的弱点部位，被攻击到弱点部位时，部位伤害降低60%。"
  },
  "弱点重击": {
    "1": "对弱点施展重击，攻击到目标弱点部位时，有25%概率使本次部位伤害提升15%。",
    "2": "对弱点施展重击，攻击到目标弱点部位时，有25%概率使本次部位伤害提升20%。",
    "3": "对弱点施展重击，攻击到目标弱点部位时，有25%概率使本次部位伤害提升25%。"
  },
  "强力攻击": {
    "1": "天生蛮力，攻击力提升3%。",
    "2": "天生蛮力，攻击力提升6%。",
    "3": "天生蛮力，攻击力提升9%。"
  },
  "强化防御": {
    "1": "防御能力异于常人，防御力提升3%。",
    "2": "防御能力异于常人，防御力提升6%。",
    "3": "防御能力异于常人，防御力提升9%。"
  },
  "强韧愈合": {
    "1": "生命值高于70%以上时受到伤害，每秒恢复基于防御力10%的生命至满。",
    "2": "生命值高于70%以上时受到伤害，每秒恢复基于防御力20%的生命至满。",
    "3": "生命值高于70%以上时受到伤害，每秒恢复基于防御力30%的生命至满。"
  },
  "微风劲雨": {
    "1": "使自己的移动速度永久降低10%，但使自身攻击速度提升10%。",
    "2": "使自己的移动速度永久降低20%，但使自身攻击速度提升20%。",
    "3": "使自己的移动速度永久降低30%，但使自身攻击速度提升30%。"
  },
  "心念合一": {
    "1": "攻势凌厉身心合一，攻击命中目标时有10%的概率使自己进入心流，在5s内自己所有概率触发的天赋必定触发。（冷却时间25s）",
    "2": "攻势凌厉身心合一，攻击命中目标时有15%的概率使自己进入心流，在7.5s内自己所有概率触发的天赋必定触发。（冷却时间25s）",
    "3": "攻势凌厉身心合一，攻击命中目标时有20%的概率使自己进入心流，在10s内自己所有概率触发的天赋必定触发。（冷却时间25s）"
  },
  "心术不正": {
    "1": "心存险恶擅长制造谣言蛊惑人心，背叛部落时最多会带走1名低认同度的族人。",
    "2": "心存险恶擅长制造谣言蛊惑人心，背叛部落时最多会带走2名低认同度的族人。",
    "3": "心存险恶擅长制造谣言蛊惑人心，背叛部落时最多会带走3名低认同度的族人。"
  },
  "忍耐": {
    "1": "成功防御敌人的攻击后，使自身防御力提升30%持续12s，在此期间不会被造成暴击。(冷却时间30s)",
    "2": "成功防御敌人的攻击后，使自身防御力提升50%持续12s，在此期间不会被造成暴击。(冷却时间30s)",
    "3": "成功防御敌人的攻击后，使自身防御力提升80%持续12s，在此期间不会被造成暴击。(冷却时间30s)"
  },
  "忍耐爆发": {
    "1": "【火石专属】忍无可忍则无需再忍，成功防御攻击且体力在60%以上则会恢复10点韧性，并获得一层防御力提升10%的效果，累计层数超过5层时进入爆发时刻6秒内造成的伤害提升50%。",
    "2": "【火石专属】忍无可忍则无需再忍，成功防御攻击且体力在60%以上则会恢复20点韧性，并获得一层防御力提升10%的效果，累计层数超过5层时进入爆发时刻6秒内造成的伤害提升75%。",
    "3": "【火石专属】忍无可忍则无需再忍，成功防御攻击且体力在60%以上则会恢复30点韧性，并获得一层防御力提升10%的效果，累计层数超过5层时进入爆发时刻6秒内造成的伤害提升100%。"
  },
  "忍辱负重": {
    "1": "受到鞭策激活潜能，受到攻击时有30%的概率，10秒内最大负重提升20%。(冷却时间30s)",
    "2": "受到鞭策激活潜能，受到攻击时有30%的概率，10秒内最大负重提升30%。(冷却时间30s)",
    "3": "受到鞭策激活潜能，受到攻击时有30%的概率，10秒内最大负重提升50%。(冷却时间30s)"
  },
  "快速包扎": {
    "1": "曾经多次在部落组织的包扎大赛中获得季军，使用绷带时包扎时间缩短30%。",
    "2": "曾经多次在部落组织的包扎大赛中获得亚军，使用绷带时包扎时间缩短40%。",
    "3": "曾经多次在部落组织的包扎大赛中获得冠军，使用绷带时包扎时间缩短50%。"
  },
  "快速吸收（水）": {
    "1": "喝的多排的也快，水分消耗提升10%。",
    "2": "喝的多排的也快，水分消耗提升30%。",
    "3": "喝的多排的也快，水分消耗提升50%。"
  },
  "快速吸收（食）": {
    "1": "吃的多又拉的快，食物消耗提升10%。",
    "2": "吃的多又拉的快，食物消耗提升30%。",
    "3": "吃的多又拉的快，食物消耗提升50%。"
  },
  "快速射击": {
    "1": "【猎手专属】极难掌握的弓类武器射击技巧，使用弓类武器拉满弓的蓄力时间缩短15%。",
    "2": "【猎手专属】极难掌握的弓类武器射击技巧，使用弓类武器拉满弓的蓄力时间缩短35%。",
    "3": "【猎手专属】极难掌握的弓类武器射击技巧，使用弓类武器拉满弓的蓄力时间缩短55%。"
  },
  "快速成长": {
    "1": "善于反思过往，角色获得的成长经验提升30%。",
    "2": "善于反思过往，角色获得的成长经验提升50%。",
    "3": "善于反思过往，角色获得的成长经验提升80%。"
  },
  "快速装填": {
    "1": "这家伙打小就聪明各种器械一学就会，使用弩箭塔、攻城弩炮时装填速度缩短20%。",
    "2": "这家伙打小就聪明各种器械一学就会，使用弩箭塔、攻城弩炮时装填速度缩短35%。",
    "3": "这家伙打小就聪明各种器械一学就会，使用弩箭塔、攻城弩炮时装填速度缩短50%。"
  },
  "怒火倾泻": {
    "1": "【毒牙专属】积蓄怒火一击致命，受到攻击时有20%的概率触发累积4s内受到的所有伤害，在累积结束后的8s内攻击到敌人时将对其释放累积的所有伤害（冷却时间30s）。",
    "2": "【毒牙专属】积蓄怒火一击致命，受到攻击时有20%的概率触发累积6s内受到的所有伤害，在累积结束后的8s内攻击到敌人时将对其释放累积的所有伤害（冷却时间30s）。",
    "3": "【毒牙专属】积蓄怒火一击致命，受到攻击时有20%的概率触发累积8s内受到的所有伤害，在累积结束后的8s内攻击到敌人时将对其释放累积的所有伤害（冷却时间30s）。"
  },
  "怒焰焚身": {
    "1": "【利爪专属】减轻火焰所造成的烧伤效果，被点燃时每次攻击敌人获得一层伤害提升效果，提升值等同于点燃伤害，至多叠加10层。",
    "2": "【利爪专属】减轻火焰所造成的烧伤效果，被点燃时每次攻击敌人获得一层伤害提升效果，提升值为1.5倍的点燃伤害，至多叠加10层。",
    "3": "【利爪专属】减轻火焰所造成的烧伤效果，被点燃时每次攻击敌人获得一层伤害提升效果，提升值为2倍的点燃伤害，至多叠加10层。"
  },
  "性格·懒惰": {
    "1": "天性懒惰不思进取，在生活和战斗行为时经常以逸待劳效率低下，同时也不易受外界影响。",
    "2": "天性懒惰不思进取，在生活和战斗行为时经常以逸待劳效率低下，同时也不易受外界影响。",
    "3": "天性懒惰不思进取，在生活和战斗行为时经常以逸待劳效率低下，同时也不易受外界影响。"
  },
  "性格·懦弱": {
    "1": "遇事慌张唯唯诺诺，在生活和战斗行为时容易心态失衡导致溃败。",
    "2": "遇事慌张唯唯诺诺，在生活和战斗行为时容易心态失衡导致溃败。",
    "3": "遇事慌张唯唯诺诺，在生活和战斗行为时容易心态失衡导致溃败。"
  },
  "性格·温和": {
    "1": "天性温和，在生活和战斗时行为比较正常，做出异常行为的概率较低。",
    "2": "天性温和，在生活和战斗时行为比较正常，做出异常行为的概率较低。",
    "3": "天性温和，在生活和战斗时行为比较正常，做出异常行为的概率较低。"
  },
  "性格·激进": {
    "1": "个性激进富有感染力，在生活和战斗时执行力强，勇往直前绝不退让。",
    "2": "个性激进富有感染力，在生活和战斗时执行力强，勇往直前绝不退让。",
    "3": "个性激进富有感染力，在生活和战斗时执行力强，勇往直前绝不退让。"
  },
  "性格·狂躁": {
    "1": "个性狂躁满腔怒火，在生活和战斗行为时不计后果，破坏力较强。",
    "2": "个性狂躁满腔怒火，在生活和战斗行为时不计后果，破坏力较强。",
    "3": "个性狂躁满腔怒火，在生活和战斗行为时不计后果，破坏力较强。"
  },
  "性格·谨慎": {
    "1": "天性谨慎，在生活和战斗时行为更加严谨，做出异常行为的概率降低。",
    "2": "天性谨慎，在生活和战斗时行为更加严谨，做出异常行为的概率降低。",
    "3": "天性谨慎，在生活和战斗时行为更加严谨，做出异常行为的概率降低。"
  },
  "恐怖嗜好": {
    "3": "难以启齿，却无法自拔，身上沾满粪便更加兴奋，食用时会获得60点心情值，并在15分钟内心情值下降速率降低70%，获得心情值时提升125%。（在此期间可使心情达到非常愉快状态）"
  },
  "恶意": {
    "1": "对状态异常的敌人心生恶意，攻击5米内处于中毒、烧伤、流血状态的目标时，有15%的概率使自己获得一层暴击率提升1%、暴击伤害提升2%的效果，持续10s，至多叠加5层。",
    "2": "对状态异常的敌人心生恶意，攻击5米内处于中毒、烧伤、流血状态的目标时，有15%的概率使自己获得一层暴击率提升2%、暴击伤害提升3%的效果，持续10s，至多叠加5层。",
    "3": "对状态异常的敌人心生恶意，攻击5米内处于中毒、烧伤、流血状态的目标时，有15%的概率使自己获得一层暴击率提升3%、暴击伤害提升4%的效果，持续10s，至多叠加5层。"
  },
  "悄无声息": {
    "1": "轻手轻脚，发出所有声音降低10%。",
    "2": "轻手轻脚，发出所有声音降低30%。",
    "3": "轻手轻脚，发出所有声音降低50%。"
  },
  "惊天动地": {
    "1": "未见其人先闻其声，发出的所有声音提高40%。",
    "2": "未见其人先闻其声，发出的所有声音提高70%。",
    "3": "未见其人先闻其声，发出的所有声音提高100%。"
  },
  "愈战愈勇": {
    "1": "【利爪专属】近身搏斗使人热血沸腾，攻击5米内的目标时有15%概率获得一层暴击、暴抗、暴击伤害、移动速度均提升2%的效果，持续30秒，至多叠加5层。",
    "2": "【利爪专属】近身搏斗使人热血沸腾，攻击5米内的目标时有15%概率获得一层暴击、暴抗、暴击伤害、移动速度均提升3%的效果，持续30秒，至多叠加5层。",
    "3": "【利爪专属】近身搏斗使人热血沸腾，攻击5米内的目标时有15%概率获得一层暴击、暴抗、暴击伤害、移动速度均提升4%的效果，持续30秒，至多叠加5层。"
  },
  "意志坚定": {
    "1": "【火石专属】意志坚定无法撼动，受到硬直效果时有15%的概率免疫本次硬直效果。(冷却时间5s)",
    "2": "【火石专属】意志坚定无法撼动，受到硬直效果时有20%的概率免疫本次硬直效果。(冷却时间5s)",
    "3": "【火石专属】意志坚定无法撼动，受到硬直效果时有25%的概率免疫本次硬直效果。(冷却时间5s)"
  },
  "愚钝": {
    "1": "自我意识主导身体时，面临危险产生自保反应的几率降低10%。",
    "2": "自我意识主导身体时，面临危险产生自保反应的几率降低15%。",
    "3": "自我意识主导身体时，面临危险产生自保反应的几率降低20%。"
  },
  "战术闪避": {
    "1": "【火石专属】成功闪避敌人攻击后，可清除自身天赋的冷却状态（冷却时间60s）。",
    "2": "【火石专属】成功闪避敌人攻击后，可清除自身天赋的冷却状态（冷却时间45s）。",
    "3": "【火石专属】成功闪避敌人攻击后，可清除自身天赋的冷却状态（冷却时间30s）。"
  },
  "手工能人": {
    "3": "手艺精湛，烹饪、工匠熟练度成长速度提升50%。"
  },
  "手段残忍": {
    "1": "被自己击杀的敌人死状异常惨烈，削弱尸体10米范围内的敌人使其攻击速度降低5%，暴抗降低10%，防御降低10%，持续20秒。",
    "2": "被自己击杀的敌人死状异常惨烈，削弱尸体10米范围内的敌人使其攻击速度降低10%，暴抗降低15%，防御降低15%，持续20秒。",
    "3": "被自己击杀的敌人死状异常惨烈，削弱尸体10米范围内的敌人使其攻击速度降低15%，暴抗降低20%，防御降低20%，持续20秒。"
  },
  "手臂应激": {
    "1": "手臂受到攻击时有20%概率产生应激反应，接下来受到的伤害降低20%，持续5秒。(冷却时间12s)",
    "2": "手臂受到攻击时有20%概率产生应激反应，接下来受到的伤害降低30%，持续5秒。(冷却时间12s)",
    "3": "手臂受到攻击时有20%概率产生应激反应，接下来受到的伤害降低50%，持续5秒。(冷却时间12s)"
  },
  "扼运者": {
    "3": "以无形之手扼住敌人命喉，被近距离目标伤害时使其天赋触发概率降低5%，持续12秒，至多叠加5层。"
  },
  "技巧恢复": {
    "1": "掌握精妙的恢复时机，成功弹反敌人的攻击后将恢复本次伤害15%的生命值。",
    "2": "掌握精妙的恢复时机，成功弹反敌人的攻击后将恢复本次伤害25%的生命值。",
    "3": "掌握精妙的恢复时机，成功弹反敌人的攻击后将恢复本次伤害35%的生命值。"
  },
  "抑制暴力": {
    "1": "用力量让敌人屈服，攻击命中目标时有5%的概率对其造成暴击率降低7%的效果，持续15s，至多叠加5层。",
    "2": "用力量让敌人屈服，攻击命中目标时有10%的概率对其造成暴击率降低7%的效果，持续15s，至多叠加5层。",
    "3": "用力量让敌人屈服，攻击命中目标时有15%的概率对其造成暴击率降低7%的效果，持续15s，至多叠加5层。"
  },
  "抵触下雨": {
    "1": "雨天使人烦躁，下雨时心情值下降2点，并在5分钟内心情值下降速率提升50%，获得心情值时降低20%。",
    "2": "雨天使人烦躁，下雨时心情值下降4点，并在5分钟内心情值下降速率提升75%，获得心情值时降低40%。"
  },
  "抵触下雪": {
    "1": "雪天的一切都让人厌烦，下雪时心情值下降2点，并在5分钟内心情值下降速率提升50%，获得心情值时降低20%。",
    "2": "雪天的一切都让人厌烦，下雪时心情值下降4点，并在5分钟内心情值下降速率提升75%，获得心情值时降低40%。"
  },
  "抵触主食": {
    "1": "吃到主食时会感到恶心，心情值下降2点，并在5分钟内心情值下降速率提升50%，获得心情值时降低20%。",
    "2": "吃到主食时会感到恶心，心情值下降4点，并在5分钟内心情值下降速率提升75%，获得心情值时降低40%。"
  },
  "抵触动物": {
    "1": "附近存在任何动物都会心生抵触，心情值下降2点，并在5分钟内心情值下降速率提升50%，获得心情值时降低20%。",
    "2": "附近存在任何动物都会心生抵触，心情值下降4点，并在5分钟内心情值下降速率提升75%，获得心情值时降低40%。"
  },
  "抵触寒冷": {
    "1": "身处寒冷的环境温度中时，心情值下降2点，并在5分钟内心情值下降速率提升50%，获得心情值时降低20%。",
    "2": "身处寒冷的环境温度中时，心情值下降4点，并在5分钟内心情值下降速率提升75%，获得心情值时降低40%。"
  },
  "抵触巨象": {
    "1": "附近有巨象时心生抵触，心情值下降2点，并在5分钟内心情值下降速率提升50%，获得心情值时降低20%。",
    "2": "附近有巨象时心生抵触，心情值下降4点，并在5分钟内心情值下降速率提升75%，获得心情值时降低40%。"
  },
  "抵触布制衣物": {
    "1": "抵触粗滥的服饰，装备布制衣物时，心情值下降2点，并在5分钟内心情值下降速率提升50%，获得心情值时降低20%。",
    "2": "抵触粗滥的服饰，装备布制衣物时，心情值下降4点，并在5分钟内心情值下降速率提升75%，获得心情值时降低40%。"
  },
  "抵触平庸首领": {
    "1": "该蛮人追随的首领是红色以下品质时会心生抵触，心情值下降2点，并在5分钟内心情值下降速率提升50%，获得心情值时降低20%。",
    "2": "该蛮人追随的首领是红色以下品质时会心生抵触，心情值下降4点，并在5分钟内心情值下降速率提升75%，获得心情值时降低40%。"
  },
  "抵触排泄": {
    "1": "排泄对自己来说是一件痛苦的事，排泄时心情值下降2点，并在5分钟内心情值下降速率提升50%，获得心情值时降低20%。",
    "2": "排泄对自己来说是一件痛苦的事，排泄时心情值下降4点，并在5分钟内心情值下降速率提升75%，获得心情值时降低40%。",
    "3": "排泄对自己来说是一件非常痛苦的事，排泄时心情值下降6点，并在5分钟内心情值下降速率提升100%，获得心情值时降低60%。（在此期间可使心情达到非常沮丧状态）"
  },
  "抵触晴天": {
    "1": "晴朗的天气让人感到不适，晴天时心情值下降2点，并在5分钟内心情值下降速率提升50%，获得心情值时降低20%。",
    "2": "晴朗的天气让人感到不适，晴天时心情值下降4点，并在5分钟内心情值下降速率提升75%，获得心情值时降低40%。"
  },
  "抵触果蔬": {
    "1": "吃到果蔬时，心情值下降2点，并在5分钟内心情值下降速率提升50%，获得心情值时降低20%。",
    "2": "吃到果蔬时，心情值下降4点，并在5分钟内心情值下降速率提升75%，获得心情值时降低40%。"
  },
  "抵触水域": {
    "1": "生活区域周围有水域时，心情值下降2点，并在5分钟内心情值下降速率提升50%，获得心情值时降低20%。",
    "2": "生活区域周围有水域时，心情值下降4点，并在5分钟内心情值下降速率提升75%，获得心情值时降低40%。"
  },
  "抵触河马": {
    "1": "附近有河马时心生抵触，心情值下降2点，并在5分钟内心情值下降速率提升50%，获得心情值时降低20%。",
    "2": "附近有河马时心生抵触，心情值下降4点，并在5分钟内心情值下降速率提升75%，获得心情值时降低40%。"
  },
  "抵触洗澡": {
    "1": "抵触洗澡，洗澡时心情值下降2点，并在5分钟内心情值下降速率提升50%，获得心情值时降低20%。",
    "2": "抵触洗澡，洗澡时心情值下降4点，并在5分钟内心情值下降速率提升75%，获得心情值时降低40%。"
  },
  "抵触清寒": {
    "1": "身处清寒的环境温度中时，心情值下降2点，并在5分钟内心情值下降速率提升50%，获得心情值时降低20%。",
    "2": "身处清寒的环境温度中时，心情值下降4点，并在5分钟内心情值下降速率提升75%，获得心情值时降低40%。"
  },
  "抵触温热": {
    "1": "身处温热的环境温度中时，心情值下降2点，并在5分钟内心情值下降速率提升50%，获得心情值时降低20%。",
    "2": "身处温热的环境温度中时，心情值下降4点，并在5分钟内心情值下降速率提升75%，获得心情值时降低40%。"
  },
  "抵触火烈鸟": {
    "1": "附近有火烈鸟时心生抵触，心情值下降2点，并在5分钟内心情值下降速率提升50%，获得心情值时降低20%。",
    "2": "附近有火烈鸟时心生抵触，心情值下降4点，并在5分钟内心情值下降速率提升75%，获得心情值时降低40%。"
  },
  "抵触炎热": {
    "1": "身处炎热的环境温度中时，心情值下降2点，并在5分钟内心情值下降速率提升50%，获得心情值时降低20%。",
    "2": "身处炎热的环境温度中时，心情值下降4点，并在5分钟内心情值下降速率提升75%，获得心情值时降低40%。"
  },
  "抵触烟草": {
    "1": "抵触烟草的味道，吸食烟草时，心情值下降2点，并在5分钟内心情值下降速率提升50%，获得心情值时降低20%。",
    "2": "抵触烟草的味道，吸食烟草时，心情值下降4点，并在5分钟内心情值下降速率提升75%，获得心情值时降低40%。"
  },
  "抵触犀牛": {
    "1": "附近有犀牛时心生抵触，心情值下降2点，并在5分钟内心情值下降速率提升50%，获得心情值时降低20%。",
    "2": "附近有犀牛时心生抵触，心情值下降4点，并在5分钟内心情值下降速率提升75%，获得心情值时降低40%。"
  },
  "抵触犰狳蜥": {
    "1": "附近有犰狳蜥时心生抵触，心情值下降2点，并在5分钟内心情值下降速率提升50%，获得心情值时降低20%。",
    "2": "附近有犰狳蜥时心生抵触，心情值下降4点，并在5分钟内心情值下降速率提升75%，获得心情值时降低40%。"
  },
  "抵触猴子": {
    "1": "调皮的猴子有些令人讨厌，附近有猴子存在时心情值下降2点，并在5分钟内心情值下降速率提升50%，获得心情值时降低20%。",
    "2": "调皮的猴子有些令人讨厌，附近有猴子存在时心情值下降4点，并在5分钟内心情值下降速率提升75%，获得心情值时降低40%。"
  },
  "抵触番茄": {
    "1": "吃到番茄时，心情值下降2点，并在5分钟内心情值下降速率提升50%，获得心情值时降低20%。",
    "2": "吃到番茄时，心情值下降4点，并在5分钟内心情值下降速率提升75%，获得心情值时降低40%。"
  },
  "抵触皮质衣物": {
    "1": "装备皮质衣物时，心情值下降2点，并在5分钟内心情值下降速率提升50%，获得心情值时降低20%。",
    "2": "装备皮质衣物时，心情值下降4点，并在5分钟内心情值下降速率提升75%，获得心情值时降低40%。"
  },
  "抵触石制武器": {
    "1": "不喜欢粗糙的武器，装备石制武器时，心情值下降2点，并在5分钟内心情值下降速率提升50%，获得心情值时降低20%。",
    "2": "不喜欢粗糙的武器，装备石制武器时，心情值下降4点，并在5分钟内心情值下降速率提升75%，获得心情值时降低40%。"
  },
  "抵触羊驼和大羊驼": {
    "1": "对羊驼和大羊驼十分抵触，附近有此类动物存在时心情值下降2点，并在5分钟内心情值下降速率提升50%，获得心情值时降低20%。",
    "2": "对羊驼和大羊驼十分抵触，附近有此类动物存在时心情值下降4点，并在5分钟内心情值下降速率提升75%，获得心情值时降低40%。"
  },
  "抵触群居": {
    "1": "待在超过10人的部落时心生厌烦，心情值下降2点，并在5分钟内心情值下降速率提升50%，获得心情值时降低20%。",
    "2": "待在超过10人的部落时心生厌烦，心情值下降4点，并在5分钟内心情值下降速率提升75%，获得心情值时降低40%。"
  },
  "抵触肉食": {
    "1": "吃到肉类食物时，心情值下降2点，并在5分钟内心情值下降速率提升50%，获得心情值时降低20%。",
    "2": "吃到肉类食物时，心情值下降4点，并在5分钟内心情值下降速率提升75%，获得心情值时降低40%。"
  },
  "抵触舒适温度": {
    "1": "身处舒适的环境温度中时，心情值下降2点，并在5分钟内心情值下降速率提升50%，获得心情值时降低20%。",
    "2": "身处舒适的环境温度中时，心情值下降4点，并在5分钟内心情值下降速率提升75%，获得心情值时降低40%。"
  },
  "抵触象龟": {
    "1": "附近有象龟时心生抵触，心情值下降2点，并在5分钟内心情值下降速率提升50%，获得心情值时降低20%。",
    "2": "附近有象龟时心生抵触，心情值下降4点，并在5分钟内心情值下降速率提升75%，获得心情值时降低40%。"
  },
  "抵触豹子": {
    "1": "对豹子的恐惧难以克服，附近有豹子存在时心情值下降2点，并在5分钟内心情值下降速率提升50%，获得心情值时降低20%。",
    "2": "对豹子的恐惧难以克服，附近有豹子存在时心情值下降4点，并在5分钟内心情值下降速率提升75%，获得心情值时降低40%。"
  },
  "抵触起床": {
    "1": "每次起床时情绪很差，心情值下降2点，并在5分钟内心情值下降速率提升50%，获得心情值时降低20%。",
    "2": "每次起床时情绪很差，心情值下降4点，并在5分钟内心情值下降速率提升75%，获得心情值时降低40%。"
  },
  "抵触跳舞": {
    "1": "四肢不够协调对跳舞比较抵触，跳舞时心情值下降2点，并在5分钟内心情值下降速率提升50%，获得心情值时降低20%。",
    "2": "四肢不够协调对跳舞比较抵触，跳舞时心情值下降4点，并在5分钟内心情值下降速率提升75%，获得心情值时降低40%。"
  },
  "抵触酱熟肉": {
    "1": "吃到酱熟肉时，心情值下降2点，并在5分钟内心情值下降速率提升50%，获得心情值时降低20%。",
    "2": "吃到酱熟肉时，心情值下降4点，并在5分钟内心情值下降速率提升75%，获得心情值时降低40%。"
  },
  "抵触野猪": {
    "1": "附近有野猪时心生抵触，心情值下降2点，并在5分钟内心情值下降速率提升50%，获得心情值时降低20%。",
    "2": "附近有野猪时心生抵触，心情值下降4点，并在5分钟内心情值下降速率提升75%，获得心情值时降低40%。"
  },
  "抵触长角牛": {
    "1": "附近有长角牛时心生抵触，心情值下降2点，并在5分钟内心情值下降速率提升50%，获得心情值时降低20%。",
    "2": "附近有长角牛时心生抵触，心情值下降4点，并在5分钟内心情值下降速率提升75%，获得心情值时降低40%。"
  },
  "抵触青铜护甲": {
    "1": "装备青铜护甲时，心情值下降2点，并在5分钟内心情值下降速率提升50%，获得心情值时降低20%。",
    "2": "装备青铜护甲时，心情值下降4点，并在5分钟内心情值下降速率提升75%，获得心情值时降低40%。"
  },
  "抵触青铜武器": {
    "1": "装备青铜武器时，心情值下降2点，并在5分钟内心情值下降速率提升50%，获得心情值时降低20%。",
    "2": "装备青铜武器时，心情值下降4点，并在5分钟内心情值下降速率提升75%，获得心情值时降低40%。"
  },
  "抵触食人鱼": {
    "1": "附近有食人鱼时心生抵触，心情值下降2点，并在5分钟内心情值下降速率提升50%，获得心情值时降低20%。",
    "2": "附近有食人鱼时心生抵触，心情值下降4点，并在5分钟内心情值下降速率提升75%，获得心情值时降低40%。"
  },
  "抵触饮酒": {
    "1": "不喜欢酒水的气味，喝酒时心情值下降2点，并在5分钟内心情值下降速率提升50%，获得心情值时降低20%。",
    "2": "不喜欢酒水的气味，喝酒时心情值下降4点，并在5分钟内心情值下降速率提升75%，获得心情值时降低40%。"
  },
  "抵触驴": {
    "1": "附近有驴时心生抵触，心情值下降2点，并在5分钟内心情值下降速率提升50%，获得心情值时降低20%。",
    "2": "附近有驴时心生抵触，心情值下降4点，并在5分钟内心情值下降速率提升75%，获得心情值时降低40%。"
  },
  "抵触骆驼": {
    "1": "附近有骆驼时心生抵触，心情值下降2点，并在5分钟内心情值下降速率提升50%，获得心情值时降低20%。",
    "2": "附近有骆驼时心生抵触，心情值下降4点，并在5分钟内心情值下降速率提升75%，获得心情值时降低40%。"
  },
  "抵触骨制武器": {
    "1": "装备骨制武器时，心情值下降2点，并在5分钟内心情值下降速率提升50%，获得心情值时降低20%。",
    "2": "装备骨制武器时，心情值下降4点，并在5分钟内心情值下降速率提升75%，获得心情值时降低40%。"
  },
  "抵触鸡": {
    "1": "附近有鸡时心生抵触，心情值下降2点，并在5分钟内心情值下降速率提升50%，获得心情值时降低20%。",
    "2": "附近有鸡时心生抵触，心情值下降4点，并在5分钟内心情值下降速率提升75%，获得心情值时降低40%。"
  },
  "抵触鸵鸟": {
    "1": "抵触鸵鸟，附近有鸵鸟存在时心情值下降2点，并在5分钟内心情值下降速率提升50%，获得心情值时降低20%。",
    "2": "抵触鸵鸟，附近有鸵鸟存在时心情值下降4点，并在5分钟内心情值下降速率提升75%，获得心情值时降低40%。"
  },
  "抵触鹦鹉": {
    "1": "聒噪的鹦鹉令人厌烦，附近有鹦鹉存在时心情值下降2点，并在5分钟内心情值下降速率提升50%，获得心情值时降低20%。",
    "2": "聒噪的鹦鹉令人厌烦，附近有鹦鹉存在时心情值下降4点，并在5分钟内心情值下降速率提升75%，获得心情值时降低40%。"
  },
  "拳套减伤": {
    "1": "使用拳套威胁减弱，使用拳套类武器造成的伤害降低10%。",
    "2": "使用拳套威胁减弱，使用拳套类武器造成的伤害降低15%。",
    "3": "使用拳套威胁减弱，使用拳套类武器造成的伤害降低20%。"
  },
  "拳套增伤": {
    "1": "使用拳套威力更强，拳套类武器造成的伤害提升3%。",
    "2": "使用拳套威力更强，拳套类武器造成的伤害提升6%。",
    "3": "使用拳套威力更强，拳套类武器造成的伤害提升9%。"
  },
  "挫敌锐气": {
    "1": "【利爪专属】凶猛的攻势让敌人闻风丧胆，攻击命中目标时有5%的概率对其造成攻击降低3%，防御降低2%，移动速度降低5%的效果，持续15s，至多叠加5层。",
    "2": "【利爪专属】凶猛的攻势让敌人闻风丧胆，攻击命中目标时有10%的概率对其造成攻击降低3%，防御降低2%，移动速度降低5%的效果，持续15s，至多叠加5层。",
    "3": "【利爪专属】凶猛的攻势让敌人闻风丧胆，攻击命中目标时有15%的概率对其造成攻击降低3%，防御降低2%，移动速度降低5%的效果，持续15s，至多叠加5层。"
  },
  "撕裂伤口": {
    "1": "【毒牙专属】破坏伤口，对正在流血的目标造成的伤害提升5%",
    "2": "【毒牙专属】破坏伤口，对正在流血的目标造成的伤害提升10%。",
    "3": "【毒牙专属】破坏伤口，对正在流血的目标造成的伤害提升15%。"
  },
  "擅长肉搏": {
    "1": "热衷于近身缠斗，对5米内敌人造成的伤害提升3%。",
    "2": "热衷于近身缠斗，对5米内敌人造成的伤害提升6%。",
    "3": "热衷于近身缠斗，对5米内敌人造成的伤害提升9%。"
  },
  "攫体化血": {
    "1": "生命值低于50%时触发，在8秒内受到的伤害将转换为同比例的体力伤害，在此期间体力不会自然恢复，直至体力耗尽。（冷却时间30秒）",
    "2": "生命值低于50%时触发，在10秒内受到的伤害将转换为同比例的体力伤害，在此期间体力不会自然恢复，直至体力耗尽。（冷却时间30秒）",
    "3": "生命值低于50%时触发，在12秒内受到的伤害将转换为同比例的体力伤害，在此期间体力不会自然恢复，直至体力耗尽。（冷却时间30秒）"
  },
  "攫体化韧": {
    "1": "生命值低于50%时触发，在8秒内受到的韧性伤害转换为体力伤害，在此期间体力不会自然恢复，直至体力殆尽。（冷却时间30秒）",
    "2": "生命值低于50%时触发，在10秒内受到的韧性伤害转换为体力伤害，在此期间体力不会自然恢复，直至体力殆尽。（冷却时间30秒）",
    "3": "生命值低于50%时触发，在12秒内受到的韧性伤害转换为体力伤害，在此期间体力不会自然恢复，直至体力殆尽。（冷却时间30秒）"
  },
  "攻其不备": {
    "1": "每个部位都有弱点，有10%概率将攻击命中的任意部位都视为弱点部位。",
    "2": "每个部位都有弱点，有15%概率将攻击命中的任意部位都视为弱点部位。",
    "3": "每个部位都有弱点，有20%概率将攻击命中的任意部位都视为弱点部位。"
  },
  "攻击弱化": {
    "1": "手无缚猪之力，攻击力降低3%。",
    "2": "手无缚猪之力，攻击力降低6%。",
    "3": "手无缚猪之力，攻击力降低9%。"
  },
  "攻击窃取": {
    "1": "【战士专属】攻击命中目标时有5%概率触发，窃取目标当前10%攻击（至多30点），转化为自身的提升，持续12秒，至多叠加5层。",
    "2": "【战士专属】攻击命中目标时有10%概率触发，窃取目标当前10%攻击（至多30点），转化为自身的提升，持续12秒，至多叠加5层。",
    "3": "【战士专属】攻击命中目标时有15%概率触发，窃取目标当前10%攻击（至多30点），转化为自身的提升，持续12秒，至多叠加5层。"
  },
  "攻势凌厉": {
    "1": "攻势凌厉，攻速提升3%。",
    "2": "攻势凌厉，攻速提升6%。",
    "3": "攻势凌厉，攻速提升9%。"
  },
  "攻势羸弱": {
    "1": "攻势绵弱，攻击速度降低5%。",
    "2": "攻势绵弱，攻击速度降低10%。",
    "3": "攻势绵弱，攻击速度降低15%。"
  },
  "攻速窃取": {
    "1": "【荒狼专属】攻击命中目标时有5%概率触发，窃取目标5%的攻击速度，转化为自身的提升，持续10秒，至多叠加5层。",
    "2": "【荒狼专属】攻击命中目标时有10%概率触发，窃取目标5%的攻击速度，转化为自身的提升，持续10秒，至多叠加5层。",
    "3": "【荒狼专属】攻击命中目标时有15%概率触发，窃取目标5%的攻击速度，转化为自身的提升，持续10秒，至多叠加5层。"
  },
  "攻防共鸣·攻": {
    "1": "攻击命中目标时有10%概率触发，提升自身「攻击力」与「防御力」中较低的一项，幅度为较高项的20%，持续12秒。（冷却时间60秒）",
    "2": "攻击命中目标时有15%概率触发，提升自身「攻击力」与「防御力」中较低的一项，幅度为较高项的20%，持续12秒。（冷却时间45秒）",
    "3": "攻击命中目标时有20%概率触发，提升自身「攻击力」与「防御力」中较低的一项，幅度为较高项的20%，持续12秒。（冷却时间30秒）"
  },
  "攻防共鸣·防": {
    "1": "防御敌人攻击时有15%概率触发，提升自身「攻击力」与「防御力」中较低的一项，幅度为较高项的20%，持续12秒。（冷却时间60秒）",
    "2": "防御敌人攻击时有20%概率触发，提升自身「攻击力」与「防御力」中较低的一项，幅度为较高项的20%，持续12秒。（冷却时间45秒）",
    "3": "防御敌人攻击时有25%概率触发，提升自身「攻击力」与「防御力」中较低的一项，幅度为较高项的20%，持续12秒。（冷却时间30秒）"
  },
  "攻防流转·攻": {
    "1": "攻击命中目标时有5%概率触发，将当前全部防御力按50%比例转换为攻击力，持续12秒。（冷却时间60秒）",
    "2": "攻击命中目标时有10%概率触发，将当前全部防御力按50%比例转换为攻击力，持续12秒。（冷却时间45秒）",
    "3": "攻击命中目标时有15%概率触发，将当前全部防御力按50%比例转换为攻击力，持续12秒。（冷却时间30秒）"
  },
  "攻防流转·防": {
    "1": "防御敌人攻击时有10%概率触发，将当前一半攻击力按200%比例转化为防御力，持续12秒。（冷却时间60秒）",
    "2": "防御敌人攻击时有15%概率触发，将当前一半攻击力按200%比例转化为防御力，持续12秒。（冷却时间45秒）",
    "3": "防御敌人攻击时有20%概率触发，将当前一半攻击力按200%比例转化为防御力，持续12秒。（冷却时间30秒）"
  },
  "敌陨狂热": {
    "1": "每当有敌人战败则会愈发兴奋，自己10米内有敌人濒死或死亡时，获得1次抵挡攻击伤害的效果，受到攻击即消耗1次。（冷却时间40s）",
    "2": "每当有敌人战败则会愈发兴奋，自己10米内有敌人濒死或死亡时，获得2次抵挡攻击伤害的效果，受到攻击即消耗1次。（冷却时间40s）",
    "3": "每当有敌人战败则会愈发兴奋，自己10米内有敌人濒死或死亡时，获得3次抵挡攻击伤害的效果，受到攻击即消耗1次。（冷却时间40s）"
  },
  "斧头杀手": {
    "3": "祖传的飞斧绝活能够使猎物变得脆弱，使用飞斧命中目标时使其在10s内受到的伤害提升10%。"
  },
  "断骨者": {
    "3": "掌握着威力强大的大剑技巧，使用大剑「蓄力重击」时，适时松开按键能够挥出更加强力的斩击。"
  },
  "无畏者": {
    "3": "以失去闪避能力为代价，换来不受任何硬直的能力。"
  },
  "易焚者": {
    "3": "油腻的身体仿佛浸过油罐，身体被点燃时受到的燃烧伤害翻倍。"
  },
  "暴击窃取": {
    "1": "攻击命中目标时有5%概率触发，窃取目标5%暴击、10%暴伤提升，转化为自身的提升，持续12秒，至多叠加5层。",
    "2": "攻击命中目标时有10%概率触发，窃取目标5%暴击、10%暴伤提升，转化为自身的提升，持续12秒，至多叠加5层。",
    "3": "攻击命中目标时有15%概率触发，窃取目标5%暴击、10%暴伤提升，转化为自身的提升，持续12秒，至多叠加5层。"
  },
  "暴抗窃取": {
    "1": "攻击命中目标时有5%概率触发，窃取目标5%暴抗、10%暴伤减免，转化为自身的提升，持续12秒，至多叠加5层。",
    "2": "攻击命中目标时有10%概率触发，窃取目标5%暴抗、10%暴伤减免，转化为自身的提升，持续12秒，至多叠加5层。",
    "3": "攻击命中目标时有15%概率触发，窃取目标5%暴抗、10%暴伤减免，转化为自身的提升，持续12秒，至多叠加5层。"
  },
  "暴走": {
    "1": "身体存在点燃、中毒、流血任意减益效果时，进入5秒「暴走」状态：增加20%攻速、移速，对目标造成伤害的20%转化为生命恢复，免疫绝大部分减速效果。（冷却时间60秒）",
    "2": "身体存在点燃、中毒、流血任意减益效果时，进入10秒「暴走」状态：增加20%攻速、移速，对目标造成伤害的20%转化为生命恢复，免疫绝大部分减速效果。（冷却时间45秒）",
    "3": "身体存在点燃、中毒、流血任意减益效果时，进入15秒「暴走」状态：增加20%攻速、移速，对目标造成伤害的20%转化为生命恢复，免疫绝大部分减速效果。（冷却时间30秒）"
  },
  "木石加速": {
    "1": "【杂工专属】手脚麻利，完成木石工作的时间缩短10%。",
    "2": "【杂工专属】手脚麻利，完成木石工作的时间缩短20%。",
    "3": "【杂工专属】手脚麻利，完成木石工作的时间缩短30%。"
  },
  "机敏": {
    "1": "自我意识主导身体时，面临危险产生反应的概率提升10%。",
    "2": "自我意识主导身体时，面临危险产生反应的概率提升20%。",
    "3": "自我意识主导身体时，面临危险产生反应的概率提升35%。"
  },
  "极限闪避": {
    "1": "成功闪避敌人攻击后立即恢复15点体力。",
    "2": "成功闪避敌人攻击后立即恢复25点体力。",
    "3": "成功闪避敌人攻击后立即恢复35点体力。"
  },
  "林中屠夫": {
    "3": "动物杀手，对非人生物造成的伤害提升10%。"
  },
  "染血荆棘": {
    "1": "当自身处于流血状态时，也会将流血效果传递给1米范围内的敌人。",
    "2": "当自身处于流血状态时，也会将流血效果传递给2米范围内的敌人。",
    "3": "当自身处于流血状态时，也会将流血效果传递给3米范围内的敌人。"
  },
  "格挡反击": {
    "1": "使用非盾牌武器防御近距离攻击时，有10%的概率额外消耗30点体力使攻击者在5秒内陷入无力状态，攻击力大幅降低。",
    "2": "使用非盾牌武器防御近距离攻击时，有15%的概率额外消耗30点体力使攻击者在5秒内陷入无力状态，攻击力大幅降低。",
    "3": "使用非盾牌武器防御近距离攻击时，有20%的概率额外消耗30点体力使攻击者在5秒内陷入无力状态，攻击力大幅降低。"
  },
  "步伐迅捷": {
    "1": "步伐迅捷，移动速度提升3%。",
    "2": "步伐迅捷，移动速度提升6%。",
    "3": "步伐迅捷，移动速度提升9%。"
  },
  "步伐迟缓": {
    "1": "腿脚迟缓，移动速度降低5%。",
    "2": "腿脚迟缓，移动速度降低10%。",
    "3": "腿脚迟缓，移动速度降低15%。"
  },
  "步履沉重": {
    "1": "脚步声音很大，移动时脚步发出的声音提高40%。",
    "2": "脚步声音很大，移动时脚步发出的声音提高70%。",
    "3": "脚步声音很大，移动时脚步发出的声音提高100%。"
  },
  "步履轻盈": {
    "1": "脚步轻盈，移动时脚步声音降低10%。",
    "2": "脚步轻盈，移动时脚步声音降低30%。",
    "3": "脚步轻盈，移动时脚步声音降低50%。"
  },
  "武器制造加速": {
    "1": "【匠人专属】对武器制造颇有心得，完成武器制造任务的时间缩短10%。",
    "2": "【匠人专属】对武器制造颇有心得，完成武器制造任务的时间缩短20%。",
    "3": "【匠人专属】对武器制造颇有心得，完成武器制造任务的时间缩短30%。"
  },
  "武器大师": {
    "3": "精通多种武器并且造诣颇高，使用任意武器造成的伤害提升10%，攻击速度提升10%。"
  },
  "武器精修": {
    "1": "【荒狼专属】身为匠人修理武器的耐久损耗降低20%。",
    "2": "【荒狼专属】身为匠人修理武器的耐久损耗降低35%。",
    "3": "【荒狼专属】身为匠人修理武器的耐久损耗降低50%。"
  },
  "武器精铸": {
    "1": "【火石专属】匠心铸造，打造武器时产出高品质概率提升5%。",
    "2": "【火石专属】匠心铸造，打造武器时产出高品质概率提升7.5%。",
    "3": "【火石专属】匠心铸造，打造武器时产出高品质概率提升10%。"
  },
  "死灰复燃": {
    "1": "在生命值回满或者从濒死回到正常状态时，使自己进入10秒「暴走」状态：增加20%攻速、移速，对目标造成伤害的20%转化为生命恢复，免疫绝大部分减速效果。（冷却时间60秒）",
    "2": "在生命值回满或者从濒死回到正常状态时，使自己进入10秒「暴走」状态：增加20%攻速、移速，对目标造成伤害的20%转化为生命恢复，免疫绝大部分减速效果。（冷却时间45秒）",
    "3": "在生命值回满或者从濒死回到正常状态时，使自己进入10秒「暴走」状态：增加20%攻速、移速，对目标造成伤害的20%转化为生命恢复，免疫绝大部分减速效果。（冷却时间30秒）"
  },
  "毒躯": {
    "1": "【毒牙专属】身体携带强力毒素，攻击命中目标时有5%概率对其造成一层持续伤害、流逝体力、精神虚弱的中毒效果，持续10秒，至多叠加5层。",
    "2": "【毒牙专属】身体携带强力毒素，攻击命中目标时有10%概率对其造成一层持续伤害、流逝体力、精神虚弱的中毒效果，持续10秒，至多叠加5层。",
    "3": "【毒牙专属】身体携带强力毒素，攻击命中目标时有15%概率对其造成一层持续伤害、流逝体力、精神虚弱的中毒效果，持续10秒，至多叠加5层。"
  },
  "气定神闲": {
    "1": "【毒牙专属】从容优雅的应对战斗，12秒内没有受到任何伤害即会获得一层攻击力提升1%，攻击速度提升2%，暴击提升2%，暴击伤害提升2%，但此阶段自身受到的伤害会少量提升，至多叠加5层，每次受到伤害即移除一层效果。",
    "2": "【毒牙专属】从容优雅的应对战斗，12秒内没有受到任何伤害即会获得一层攻击力提升1.5%，攻击速度提升2%，暴击提升2%，暴击伤害提升3%，但此阶段自身受到的伤害会少量提升，至多叠加5层，每次受到伤害即移除一层效果。",
    "3": "【毒牙专属】从容优雅的应对战斗，12秒内没有受到任何伤害即会获得一层攻击力提升2%，攻击速度提升2%，暴击提升3%，暴击伤害提升4%，但此阶段自身受到的伤害会少量提升，至多叠加5层，每次受到伤害即移除一层效果。"
  },
  "气血亏虚": {
    "1": "看起来比常人虚弱，最大生命值降低3%。",
    "2": "看起来比常人虚弱，最大生命值降低6%。",
    "3": "看起来比常人虚弱，最大生命值降低9%。"
  },
  "气血充盈": {
    "1": "面色红润有光泽，最大生命提升3%。",
    "2": "面色红润有光泽，最大生命提升6%",
    "3": "面色红润有光泽，最大生命提升9%"
  },
  "洞察防御": {
    "1": "【火石专属】洞察敌人的防守缺陷，成功弹反敌人的攻击后3s内自己的攻击可以无视敌人的防御力。（冷却时间30s）",
    "2": "【火石专属】洞察敌人的防守缺陷，成功弹反敌人的攻击后5s内自己的攻击可以无视敌人的防御力。（冷却时间30s）",
    "3": "【火石专属】洞察敌人的防守缺陷，成功弹反敌人的攻击后7s内自己的攻击可以无视敌人的防御力。（冷却时间30s）"
  },
  "活血": {
    "1": "气血旺盛，生命恢复速度提升50%。",
    "2": "气血旺盛，生命恢复速度提升100%。",
    "3": "气血旺盛，生命恢复速度提升200%。"
  },
  "流放者·寒冷抗性": {
    "1": "久居雪山的人对寒冷早已适应，寒冷抗性提升5。",
    "2": "久居雪山的人对寒冷早已适应，寒冷抗性提升10。",
    "3": "久居雪山的人对寒冷早已适应，寒冷抗性提升15。"
  },
  "流放者·炎热抗性": {
    "1": "久居炎热地带的流放者产生了天然抗性，炎热抗性提升5。",
    "2": "久居炎热地带的流放者产生了天然抗性，炎热抗性提升10。",
    "3": "久居炎热地带的流放者产生了天然抗性，炎热抗性提升15。"
  },
  "流放者·辐射抗性": {
    "1": "久居辐射地带的流放者产生了天然抗性，辐射抗性提升5。",
    "2": "久居辐射地带的流放者产生了天然抗性，辐射抗性提升10。",
    "3": "久居辐射地带的流放者产生了天然抗性，辐射抗性提升15。"
  },
  "浊血之毒": {
    "1": "攻击命中目标时有5%概率触发，使其在使用药物类道具时会累积大量毒素，持续15秒。",
    "2": "攻击命中目标时有10%概率触发，使其在使用药物类道具时会累积大量毒素，持续15秒。",
    "3": "攻击命中目标时有15%概率触发，使其在使用药物类道具时会累积大量毒素，持续15秒。"
  },
  "浴血恢复": {
    "1": "鲜血即生命，受到攻击时有20%的概率舐血恢复，每秒恢复基于自身攻击力10%的生命值，持续15s，在此期间受流血状态损失的生命将转换为同等的生命恢复。（冷却时间25s）",
    "2": "鲜血即生命，受到攻击时有20%的概率舐血恢复，每秒恢复基于自身攻击力20%的生命值，持续15s，在此期间受流血状态损失的生命将转换为1.25倍的生命恢复。（冷却时间25s）",
    "3": "鲜血即生命，受到攻击时有20%的概率舐血恢复，每秒恢复基于自身攻击力30%的生命值，持续15s，在此期间受流血状态损失的生命将转换为1.5倍的生命恢复。（冷却时间25s）"
  },
  "淬锋巧手": {
    "1": "【荒狼专属】身为匠人在制作武器时有5%的概率为其增加1条额外属性。",
    "2": "【荒狼专属】身为匠人在制作武器时有10%的概率为其增加1条额外属性。",
    "3": "【荒狼专属】身为匠人在制作武器时有10%的概率至多增加2条额外属性。"
  },
  "混乱弹反": {
    "1": "弹反敌人攻击时，使其「混乱」在6秒内移动操作反转。（冷却时间25秒）",
    "2": "弹反敌人攻击时，使其「混乱」在8秒内移动操作反转。（冷却时间25秒）",
    "3": "弹反敌人攻击时，使其「混乱」在10秒内移动操作反转。（冷却时间25秒）"
  },
  "混乱防御": {
    "1": "防御敌人攻击时有5%概率触发，使其「混乱」在5秒内移动操作反转。（冷却时间20秒）",
    "2": "防御敌人攻击时有10%概率触发，使其「混乱」在5秒内移动操作反转。（冷却时间20秒）",
    "3": "防御敌人攻击时有15%概率触发，使其「混乱」在5秒内移动操作反转。（冷却时间20秒）"
  },
  "渴望鲜血": {
    "1": "对鲜血无尽渴求，攻击5米内的目标时自己有25%的概率吸收本次伤害10%的生命值。",
    "2": "对鲜血无尽渴求，攻击5米内的目标时自己有25%的概率吸收本次伤害20%的生命值。",
    "3": "对鲜血无尽渴求，攻击5米内的目标时自己有25%的概率吸收本次伤害30%的生命值。"
  },
  "溃防冲击": {
    "1": "【蛮角专属】攻击目标时若目标在防御状态有5%的概率清空其体力破坏其防御状态。（冷却时间5秒）",
    "2": "【蛮角专属】攻击目标时若目标在防御状态有10%的概率清空其体力破坏其防御状态。（冷却时间5秒）",
    "3": "【蛮角专属】攻击目标时若目标在防御状态有15%的概率清空其体力破坏其防御状态。（冷却时间5秒）"
  },
  "滞缓之毒": {
    "1": "攻击中毒目标时有5%概率触发，使其在发动攻击或冲刺时，攻速或移速将愈发迟缓，持续15秒。",
    "2": "攻击中毒目标时有10%概率触发，使其在发动攻击或冲刺时，攻速或移速将愈发迟缓，持续15秒。",
    "3": "攻击中毒目标时有15%概率触发，使其在发动攻击或冲刺时，攻速或移速将愈发迟缓，持续15秒。"
  },
  "激发斗志": {
    "1": "【火石专属】痛苦唤醒自我仇恨激活潜能，受到攻击时有10%概率进入心流，在5s内自己所有概率触发的天赋必定触发。（冷却时间25s）",
    "2": "【火石专属】痛苦唤醒自我仇恨激活潜能，受到攻击时有15%概率进入心流，在7.5s内自己所有概率触发的天赋必定触发。（冷却时间25s）",
    "3": "【火石专属】痛苦唤醒自我仇恨激活潜能，受到攻击时有20%概率进入心流，在10s内自己所有概率触发的天赋必定触发。（冷却时间25s）"
  },
  "火势蔓延": {
    "1": "我烧起来了谁都别想跑，身体被点燃时能够将点燃效果传递给1米范围内的敌人",
    "2": "我烧起来了谁都别想跑，身体被点燃时能够将点燃效果传递给2米范围内的敌人",
    "3": "我烧起来了谁都别想跑，身体被点燃时能够将点燃效果传递给3米范围内的敌人"
  },
  "灵活逃脱": {
    "1": "留足体力随时逃脱，受到硬直效果时，恢复10点体力。(冷却时间5s)",
    "2": "留足体力随时逃脱，受到硬直效果时，恢复15点体力。(冷却时间5s)",
    "3": "留足体力随时逃脱，受到硬直效果时，恢复25点体力。(冷却时间5s)"
  },
  "炼金加速": {
    "1": "【匠人专属】对炼金颇有天份，完成炼金任务的时间缩短10%。",
    "2": "【匠人专属】对炼金颇有天份，完成炼金任务的时间缩短20%。",
    "3": "【匠人专属】对炼金颇有天份，完成炼金任务的时间缩短30%。"
  },
  "烧窑加速": {
    "1": "【杂工专属】高温作业亦不能阻挡其热情，完成烧窑工作的时间缩短10%。",
    "2": "【杂工专属】高温作业亦不能阻挡其热情，完成烧窑工作的时间缩短20%。",
    "3": "【杂工专属】高温作业亦不能阻挡其热情，完成烧窑工作的时间缩短30%。"
  },
  "烹饪加速": {
    "1": "【匠人专属】对烹饪颇有心得，在进行烹饪时完成食物的时间缩短10%。",
    "2": "【匠人专属】对烹饪颇有心得，在进行烹饪时完成食物的时间缩短20%。",
    "3": "【匠人专属】对烹饪颇有心得，在进行烹饪时完成食物的时间缩短30%。"
  },
  "燃烧威慑": {
    "1": "身体燃烧时的恐怖景象令敌人胆怯，使3米范围内的敌人攻击力、移动速度降低10%，持续10s，至多叠加3层。",
    "2": "身体燃烧时的恐怖景象令敌人胆怯，使5米范围内的敌人攻击力、移动速度降低10%，持续10s，至多叠加3层。",
    "3": "身体燃烧时的恐怖景象令敌人胆怯，使8米范围内的敌人攻击力、移动速度降低10%，持续10s，至多叠加3层。"
  },
  "燃魂狙击": {
    "1": "【猎手专属】拉弓蓄力状态下生命值持续流失，射出的箭矢将附加蓄力期间流失生命值的50%作为伤害。（额外伤害不会超过自身最大生命值）。",
    "2": "【猎手专属】拉弓蓄力状态下生命值持续流失，射出的箭矢将附加蓄力期间流失生命值的75%作为伤害。（额外伤害不会超过自身最大生命值）。",
    "3": "【猎手专属】拉弓蓄力状态下生命值持续流失，射出的箭矢将附加蓄力期间流失生命值的100%作为伤害，在恰当的时机发射可大幅提升效果。（额外伤害不会超过自身最大生命值）。"
  },
  "爆发共鸣·攻": {
    "1": "攻击命中目标时有10%概率触发，提升自身「暴击」与「暴抗」中较低的一项，幅度为较高项的30%，持续12秒。（冷却时间60秒）",
    "2": "攻击命中目标时有15%概率触发，提升自身「暴击」与「暴抗」中较低的一项，幅度为较高项的30%，持续12秒。（冷却时间45秒）",
    "3": "攻击命中目标时有20%概率触发，提升自身「暴击」与「暴抗」中较低的一项，幅度为较高项的30%，持续12秒。（冷却时间30秒）"
  },
  "爆发共鸣·防": {
    "1": "防御敌人攻击时有15%概率触发，提升自身「暴击」与「暴抗」中较低的一项，幅度为较高项的30%，持续12秒。（冷却时间60秒）",
    "2": "防御敌人攻击时有20%概率触发，提升自身「暴击」与「暴抗」中较低的一项，幅度为较高项的30%，持续12秒。（冷却时间45秒）",
    "3": "防御敌人攻击时有25%概率触发，提升自身「暴击」与「暴抗」中较低的一项，幅度为较高项的30%，持续12秒。（冷却时间30秒）"
  },
  "爆发流转·攻": {
    "1": "攻击命中目标时有5%概率触发，将当前的全部「暴抗」按50%比例转化为「暴击」，持续12秒。（冷却时间60秒）",
    "2": "攻击命中目标时有10%概率触发，将当前的全部「暴抗」按50%比例转化为「暴击」，持续12秒。（冷却时间45秒）",
    "3": "攻击命中目标时有15%概率触发，将当前的全部「暴抗」按50%比例转化为「暴击」，持续12秒。（冷却时间30秒）"
  },
  "爆发流转·防": {
    "1": "防御敌人攻击时有10%概率触发，将当前一半的「暴击」转化为「暴抗」，持续12秒。（冷却时间60秒）",
    "2": "防御敌人攻击时有15%概率触发，将当前一半的「暴击」转化为「暴抗」，持续12秒。（冷却时间45秒）",
    "3": "防御敌人攻击时有20%概率触发，将当前一半的「暴击」转化为「暴抗」，持续12秒。（冷却时间30秒）"
  },
  "爆毒之种": {
    "1": "使用武器攻击处于中毒状态的敌人有5%的概率对其施加持续5秒的「爆毒之种」：目标在翻滚和闪避时将产生爆毒，使2米范围内的目标中毒。",
    "2": "使用武器攻击处于中毒状态的敌人有10%的概率对其施加持续5秒的「爆毒之种」：目标在翻滚和闪避时将产生爆毒，使4米范围内的目标中毒。",
    "3": "使用武器攻击处于中毒状态的敌人有15%的概率对其施加持续5秒的「爆毒之种」：目标在翻滚和闪避时将产生爆毒，使6米范围内的目标中毒。"
  },
  "爆燃之种": {
    "1": "使用武器攻击处于点燃状态的敌人有5%的概率对其施加持续5秒的「爆燃之种」：目标在翻滚和闪避时将产生爆燃，使2米范围内的目标点燃。",
    "2": "使用武器攻击处于点燃状态的敌人有10%的概率对其施加持续5秒的「爆燃之种」：目标在翻滚和闪避时将产生爆燃，使4米范围内的目标点燃。",
    "3": "使用武器攻击处于点燃状态的敌人有15%的概率对其施加持续5秒的「爆燃之种」：目标在翻滚和闪避时将产生爆燃，使6米范围内的目标点燃。"
  },
  "爆血之种": {
    "1": "使用武器攻击处于流血状态的敌人有5%的概率对其施加持续5秒的「爆血之种」：目标在翻滚和闪避时将产生爆血，使2米范围内的目标流血。",
    "2": "使用武器攻击处于流血状态的敌人有10%的概率对其施加持续5秒的「爆血之种」：目标在翻滚和闪避时将产生爆血，使4米范围内的目标流血。",
    "3": "使用武器攻击处于流血状态的敌人有15%的概率对其施加持续5秒的「爆血之种」：目标在翻滚和闪避时将产生爆血，使6米范围内的目标流血。"
  },
  "牵引投掷": {
    "1": "使用飞斧、飞刀或掷矛命中目标时，可以将目标拉向自己。",
    "2": "使用飞斧、飞刀或掷矛命中目标时，可以将目标拉至身边。",
    "3": "使用飞斧、飞刀或掷矛命中目标时，可以将目标拉至身边，并使其无法翻滚，持续5秒。"
  },
  "特殊癖好": {
    "1": "怎么回事？为什么会喜欢这种味道？身上沾满粪便更加兴奋，食用时会获得20点心情值，并在15分钟内心情值下降速率降低30%，获得心情值时提升75%。"
  },
  "狡诈": {
    "1": "【荒狼专属】受到攻击时有15%概率触发，在8秒内，能将敌人施加的持续效果返还给施加者。（冷却时间60秒）",
    "2": "【荒狼专属】受到攻击时有15%概率触发，在10秒内，能将敌人施加的持续效果返还给施加者。（冷却时间45秒）",
    "3": "【荒狼专属】受到攻击时有15%概率触发，在12秒内，能将敌人施加的持续效果返还给施加者。（冷却时间30秒）"
  },
  "猛攻": {
    "1": "【战士专属】以猛兽般的攻势压制敌人，清空目标韧性时会移除其霸体状态，12s内攻击速度提升10%，若每击伤害超过目标最大生命5%则恢复体力。（冷却时间60s）",
    "2": "【战士专属】以猛兽般的攻势压制敌人，清空目标韧性时会移除其霸体状态，12s内攻击速度提升10%，若每击伤害超过目标最大生命5%则恢复体力。（冷却时间45s）",
    "3": "【战士专属】以猛兽般的攻势压制敌人，清空目标韧性时会移除其霸体状态，12s内攻击速度提升10%，若每击伤害超过目标最大生命5%则恢复体力。（冷却时间30s）"
  },
  "珠宝制造加速": {
    "1": "精通珠宝工艺流程，完成珠宝制作工作的时间缩短10%。",
    "2": "精通珠宝工艺流程，完成珠宝制作工作的时间缩短20%。",
    "3": "精通珠宝工艺流程，完成珠宝制作工作的时间缩短30%。"
  },
  "生命枷锁": {
    "1": "受到攻击时有15%概率触发，在15秒内彻底失去生命恢复能力，但每次受到伤害至多失去2%最大生命。（冷却时间60秒）",
    "2": "受到攻击时有15%概率触发，在20秒内彻底失去生命恢复能力，但每次受到伤害至多失去2%最大生命。（冷却时间60秒）",
    "3": "受到攻击时有15%概率触发，在25秒内彻底失去生命恢复能力，但每次受到伤害至多失去2%最大生命。（冷却时间60秒）"
  },
  "畏惧烈焰": {
    "1": "身体被点燃时加重受到的烧伤效果，并使自己造成的伤害降低20%",
    "2": "身体被点燃时加重受到的烧伤效果，并使自己造成的伤害降低25%。",
    "3": "身体被点燃时加重受到的烧伤效果，并使自己造成的伤害降低30%。"
  },
  "痛苦逆转": {
    "1": "将痛苦转化为动力，受到攻击时，有 5% 的概率清除自身天赋的冷却状态（冷却时间20s）。",
    "2": "将痛苦转化为动力，受到攻击时，有 10% 的概率清除自身天赋的冷却状态（冷却时间20s）。",
    "3": "将痛苦转化为动力，受到攻击时，有 15% 的概率清除自身天赋的冷却状态（冷却时间20s）。"
  },
  "直击要害": {
    "1": "双目如雄鹰般犀利，攻击15米外敌人的弱点部位时使本次部位伤害提升15%。",
    "2": "双目如雄鹰般犀利，攻击15米外敌人的弱点部位时使本次部位伤害提升20%。",
    "3": "双目如雄鹰般犀利，攻击15米外敌人的弱点部位时使本次部位伤害提升25%。"
  },
  "盾防反击": {
    "1": "掌握巧妙的盾牌防御技巧，额外消耗最大体力的10%+17点来防御近距离攻击，并对攻击者造成基于自身攻击力100%的伤害，若防御时体力低于30%则自身会受到双倍伤害。",
    "2": "掌握巧妙的盾牌防御技巧，额外消耗最大体力的10%+12点来防御近距离攻击，并对攻击者造成基于自身攻击力100%的伤害，若防御时体力低于30%则自身会受到双倍伤害。",
    "3": "掌握巧妙的盾牌防御技巧，额外消耗最大体力的10%+7点来防御近距离攻击，并对攻击者造成基于自身攻击力100%的伤害，若防御时体力低于30%则自身会受到双倍伤害。"
  },
  "矿脉守护": {
    "1": "【毒牙专属】刨矿不毁其脉，挖过的矿石再生时间缩短20%。",
    "2": "【毒牙专属】刨矿不毁其脉，挖过的矿石再生时间缩短30%。",
    "3": "【毒牙专属】刨矿不毁其脉，挖过的矿石再生时间缩短40%。"
  },
  "研磨加速": {
    "1": "精通研磨手艺，完成研磨工作的时间缩短10%。",
    "2": "精通研磨手艺，完成研磨工作的时间缩短20%。",
    "3": "精通研磨手艺，完成研磨工作的时间缩短30%。"
  },
  "破坏闪击": {
    "1": "成功闪避敌人攻击后有15%概率触发，2s内的下一次攻击暴击增加100%，并随机对其造成「混乱」「迷惑」「逆闪」其中一种效果持续6秒。（冷却时间12秒）",
    "2": "成功闪避敌人攻击后有20%概率触发，3s内的下一次攻击暴击增加100%，并随机对其造成「混乱」「迷惑」「逆闪」其中一种效果持续6秒。（冷却时间12秒）",
    "3": "成功闪避敌人攻击后有25%概率触发，4s内的下一次攻击暴击增加100%，并随机对其造成「混乱」「迷惑」「逆闪」其中一种效果持续6秒。（冷却时间12秒）"
  },
  "破箱人": {
    "3": "漂泊半生撬箱无数，无论多么精密的箱子都能够快速打开，开启箱子的速度提升80%。"
  },
  "破胆重击": {
    "1": "攻击命中近距离目标时有5%概率触发，使敌人陷入「怯战」状态，持续6秒：期间其单次伤害不会超过300点，对首领级敌人效果减弱。（冷却时间25秒）",
    "2": "攻击命中近距离目标时有10%概率触发，使敌人陷入「怯战」状态，持续6秒：期间其单次伤害不会超过300点，对首领级敌人效果减弱。（冷却时间20秒）",
    "3": "攻击命中近距离目标时有15%概率触发，使敌人陷入「怯战」状态，持续6秒：期间其单次伤害不会超过300点，对首领级敌人效果减弱。（冷却时间15秒）"
  },
  "硬化身躯": {
    "1": "面对威胁瞬间绷紧身体，受到硬直效果时有20%概率获得1秒霸体。(冷却时间5s)",
    "2": "面对威胁瞬间绷紧身体，受到硬直效果时有20%概率获得2秒霸体。(冷却时间5s)",
    "3": "面对威胁瞬间绷紧身体，受到硬直效果时有20%概率获得3秒霸体。(冷却时间5s)"
  },
  "硬皮·抗挥砍": {
    "1": "皮韧砍不开，身体受到挥砍类型伤害时受到的伤害降低10%。",
    "2": "皮韧砍不开，身体受到挥砍类型伤害时受到的伤害降低15%。",
    "3": "皮韧砍不开，身体受到挥砍类型伤害时受到的伤害降低20%。"
  },
  "硬皮·抗穿刺": {
    "1": "皮厚刺不透，身体受到穿刺类型伤害时受到的伤害降低10%。",
    "2": "皮厚刺不透，身体受到穿刺类型伤害时受到的伤害降低15%。",
    "3": "皮厚刺不透，身体受到穿刺类型伤害时受到的伤害降低20%。"
  },
  "硬皮·抗钝击": {
    "1": "皮硬砸不疼，身体受到钝击类型伤害时受到的伤害降低10%。",
    "2": "皮硬砸不疼，身体受到钝击类型伤害时受到的伤害降低15%。",
    "3": "皮硬砸不疼，身体受到钝击类型伤害时受到的伤害降低20%。"
  },
  "硬骨头": {
    "3": "没有人比他更懂挨揍，受到攻击时若当前韧性超过50%则不会被造成暴击。"
  },
  "磐石意志": {
    "1": "【卫士专属】成功防御敌人的攻击后，使自身的昏迷、麻痹、流血抗性提升30%持续12s。（冷却时间30s）",
    "2": "【卫士专属】成功防御敌人的攻击后，使自身的昏迷、麻痹、流血抗性提升50%持续12s。（冷却时间30s）",
    "3": "【卫士专属】成功防御敌人的攻击后，使自身的昏迷、麻痹、流血抗性提升80%持续12s。（冷却时间30s）"
  },
  "禁忌之躯": {
    "1": "受到攻击时有5%概率触发，使攻击者在5秒内所有天赋无法触发。（冷却时间40秒）",
    "2": "受到攻击时有10%概率触发，使攻击者在10秒内所有天赋无法触发。（冷却时间40秒）",
    "3": "受到攻击时有15%概率触发，使攻击者在15秒内所有天赋无法触发。（冷却时间40秒）"
  },
  "种植能手": {
    "1": "【毒牙专属】培育作物十分用心，自己亲手种植采摘的植物产量提升10%。",
    "2": "【毒牙专属】培育作物十分用心，自己亲手种植采摘的植物产量提升15%。",
    "3": "【毒牙专属】培育作物十分用心，自己亲手种植采摘的植物产量提升20%。"
  },
  "种田能手": {
    "3": "对种田颇有心得，亲手种植的作物成长速度提升20%。"
  },
  "移速窃取": {
    "1": "【蛮角专属】攻击命中目标时有5%概率触发，窃取目标6%的移动速度，转化为自身的提升，持续10秒，至多叠加5层。",
    "2": "【蛮角专属】攻击命中目标时有10%概率触发，窃取目标6%的移动速度，转化为自身的提升，持续10秒，至多叠加5层。",
    "3": "【蛮角专属】攻击命中目标时有15%概率触发，窃取目标6%的移动速度，转化为自身的提升，持续10秒，至多叠加5层。"
  },
  "穿肺者": {
    "3": "破坏喘息节奏使猎物感到慌乱，使用掷矛命中目标时使其体力恢复降低80%，持续10s。"
  },
  "穿透防御": {
    "1": "攻击命中目标时有5%的概率使本次攻击无视目标防御。（冷却时间2s）",
    "2": "攻击命中目标时有10%的概率使本次攻击无视目标防御。（冷却时间2s）",
    "3": "攻击命中目标时有15%的概率使本次攻击无视目标防御。（冷却时间2s）"
  },
  "竭血逐攻": {
    "1": "受到攻击时有15%概率触发，在12秒内降低自身10%最大生命换来10%的攻击力提升。（冷却时间30秒）",
    "2": "受到攻击时有20%概率触发，在12秒内降低自身30%最大生命换来30%的攻击力提升。（冷却时间30秒）",
    "3": "受到攻击时有25%概率触发，在12秒内降低自身50%最大生命换来50%的攻击力提升。（冷却时间30秒）"
  },
  "笨拙": {
    "1": "发力技巧非常粗糙，在进行需要消耗体力的行动时，体力消耗提升10%。",
    "2": "发力技巧非常粗糙，在进行需要消耗体力的行动时，体力消耗提升20%。",
    "3": "发力技巧非常粗糙，在进行需要消耗体力的行动时，体力消耗提升30%。"
  },
  "箭术大师": {
    "3": "箭矢离弦的那一刻猎物的命运已经注定，使用弓类武器有20%的概率将命中的任意部位都视为弱点部位，并使目标移动速度降低50%，持续6s。"
  },
  "粗活能手": {
    "3": "干粗活一把好手，木石、烧窑熟练度成长速度提升50%。"
  },
  "精制工具": {
    "1": "【匠人专属】工具制作独具匠心，打造工具时产出高品质的概率提升5%。",
    "2": "【匠人专属】工具制作独具匠心，打造工具时产出高品质的概率提升7.5%。",
    "3": "【匠人专属】工具制作独具匠心，打造工具时产出高品质的概率提升10%。"
  },
  "精制防具": {
    "1": "【火石专属】手艺精湛，制造防具时产出高品质概率提升5%。",
    "2": "【火石专属】手艺精湛，制造防具时产出高品质概率提升7.5%。",
    "3": "【火石专属】手艺精湛，制造防具时产出高品质概率提升10%。"
  },
  "精造巧手": {
    "3": "手艺精湛，武器制造、防具制造、炼金熟练度成长速度提升50%。"
  },
  "纺织加速": {
    "1": "【杂工专属】纺织能手，完成纺织工作的时间缩短10%。",
    "2": "【杂工专属】纺织能手，完成纺织工作的时间缩短20%。",
    "3": "【杂工专属】纺织能手，完成纺织工作的时间缩短30%。"
  },
  "细活能手": {
    "3": "做事精细，纺织、制陶、制皮的熟练度成长速度提升50%。"
  },
  "经历·能征善战": {
    "1": "经常随部落出战深谙战场生存之道，作为随从出战时受到的所有伤害降低40%。",
    "2": "经常随部落出战深谙战场生存之道，作为随从出战时受到的所有伤害降低50%。",
    "3": "经常随部落出战深谙战场生存之道，作为随从出战时受到的所有伤害降低60%。"
  },
  "绝境应激": {
    "1": "【毒牙专属】濒临死亡时激起强烈的求生欲，生命值低于30%时，每次受到攻击时至多失去5%最大生命（受到伤害超过生命上限时无法生效）。",
    "2": "【毒牙专属】濒临死亡时激起强烈的求生欲，生命值低于30%时，每次受到攻击时至多失去4%最大生命（受到伤害超过生命上限时无法生效）。",
    "3": "【毒牙专属】濒临死亡时激起强烈的求生欲，生命值低于30%时，每次受到攻击时至多失去3%最大生命（受到伤害超过生命上限时无法生效）。"
  },
  "缓慢包扎": {
    "1": "每次参加部落包扎大赛都是被当作笑柄的存在，使用绷带时包扎时间延长30%。",
    "2": "每次参加部落包扎大赛都是被当作笑柄的存在，使用绷带时包扎时间延长40%。",
    "3": "每次参加部落包扎大赛都是被当作笑柄的存在，使用绷带时包扎时间延长50%。"
  },
  "缓慢吸收（水）": {
    "1": "水分吸收慢，水分消耗降低10%。",
    "2": "水分吸收慢，水分消耗降低30%。",
    "3": "水分吸收慢，水分消耗降低50%。"
  },
  "缓慢吸收（食）": {
    "1": "食物消化更慢，食物消耗降低10%。",
    "2": "食物消化更慢，食物消耗降低30%。",
    "3": "食物消化更慢，食物消耗降低50%。"
  },
  "缓慢射击": {
    "1": "掌握拙劣的弓类武器发射技巧，使用弓类武器拉满弓的蓄力时间延长30%。",
    "2": "掌握拙劣的弓类武器发射技巧，使用弓类武器拉满弓的蓄力时间延长50%。",
    "3": "掌握拙劣的弓类武器发射技巧，使用弓类武器拉满弓的蓄力时间延长80%。"
  },
  "缓慢成长": {
    "1": "很难从经历中获取更多经验教训，角色获得的成长经验降低20%。",
    "2": "很难从经历中获取更多经验教训，角色获得的成长经验降低40%。",
    "3": "很难从经历中获取更多经验教训，角色获得的成长经验降低60%。"
  },
  "缓慢装填": {
    "1": "学不会真的学不会，使用弩箭塔、攻城弩炮时装填速度延长20%。",
    "2": "学不会真的学不会，使用弩箭塔、攻城弩炮时装填速度延长35%。",
    "3": "学不会真的学不会，使用弩箭塔、攻城弩炮时装填速度延长50%。"
  },
  "群狼庇护": {
    "1": "【荒狼专属】在生命值回满或者从濒死回到正常状态时，使自己及5米范围内的友方族人不会受到绝大多数减速效果影响，持续8秒。（冷却时间30秒）",
    "2": "【荒狼专属】在生命值回满或者从濒死回到正常状态时，使自己及7.5米范围内的友方族人不会受到绝大多数减速效果影响，持续10秒。（冷却时间30秒）",
    "3": "【荒狼专属】在生命值回满或者从濒死回到正常状态时，使自己及10米范围内的友方族人不会受到绝大多数减速效果影响，持续12秒。（冷却时间30秒）"
  },
  "群狼战魂": {
    "1": "【荒狼专属】攻击命中目标时有5%概率触发，15米范围内每名友方族人为自己提供2%伤害提升（至多5人），若为荒狼部落族人则效果提升为4%，持续20秒。（冷却时间10秒）",
    "2": "【荒狼专属】攻击命中目标时有10%概率触发，15米范围内每名友方族人为自己提供3%伤害提升（至多5人），若为荒狼部落族人则效果提升为6%，持续20秒。（冷却时间10秒）",
    "3": "【荒狼专属】攻击命中目标时有15%概率触发，15米范围内每名友方族人为自己提供4%伤害提升（至多5人），若为荒狼部落族人则效果提升为8%，持续20秒。（冷却时间10秒）"
  },
  "耐渴": {
    "1": "身体储备水分更多更加耐渴，最大水分提升20%。",
    "2": "身体储备水分更多更加耐渴，最大水分提升30%。",
    "3": "身体储备水分更多更加耐渴，最大水分提升40%。"
  },
  "耐饿": {
    "1": "身体储备食物更多更加耐饿，饱食度最大值提升20%。",
    "2": "身体储备食物更多更加耐饿，饱食度最大值提升30%。",
    "3": "身体储备食物更多更加耐饿，饱食度最大值提升40%。"
  },
  "耳聪": {
    "1": "听力敏感，能够听到的声音比常人低5分贝。",
    "2": "听力敏感，能够听到的声音比常人低10分贝。",
    "3": "听力敏感，能够听到的声音比常人低15分贝。"
  },
  "耳背": {
    "1": "听力较差，对声音不太敏感，比常人大5分贝的声音才能听到。",
    "2": "听力较差，对声音不太敏感，比常人大10分贝的声音才能听到。",
    "3": "听力较差，对声音不太敏感，比常人大15分贝的声音才能听到。"
  },
  "肢体破坏": {
    "1": "精通肢体结构，攻击到目标四肢部位时，有20%概率伤害提升10%。",
    "2": "精通肢体结构，攻击到目标四肢部位时，有20%概率伤害提升15%。",
    "3": "精通肢体结构，攻击到目标四肢部位时，有20%概率伤害提升25%。"
  },
  "背包扩容": {
    "1": "背包暗藏玄机能容纳更多物品，比常人的背包格子数量提升10格。",
    "2": "背包暗藏玄机能容纳更多物品，比常人的背包格子数量提升20格。",
    "3": "背包暗藏玄机能容纳更多物品，比常人的背包格子数量提升30格。"
  },
  "脚步笨拙": {
    "1": "掌握拙劣的弓类武器移动技巧，使用弓类武器瞄准时的移动速度降低30%。",
    "2": "掌握拙劣的弓类武器移动技巧，使用弓类武器瞄准时的移动速度降低50%。",
    "3": "掌握拙劣的弓类武器移动技巧，使用弓类武器瞄准时的移动速度降低80%。"
  },
  "腿脚灵活": {
    "2": "死亡总是慢我一小步，移动速度提升5%。"
  },
  "致命": {
    "1": "对生命值低于30%的目标造成伤害时，有20%概率使本次伤害提升15%，并对目标造成一个持续5s的隐藏伤口，在此期间冲刺时会引发重度流血，每秒流失基于自身攻击力40%的生命值。",
    "2": "对生命值低于30%的目标造成伤害时，有20%概率使本次伤害提升20%，并对目标造成一个持续5s的隐藏伤口，在此期间冲刺时会引发重度流血，每秒流失基于自身攻击力60%的生命值。",
    "3": "对生命值低于30%的目标造成伤害时，有20%概率使本次伤害提升25%，并对目标造成一个持续5s的隐藏伤口，在此期间冲刺时会引发重度流血，每秒流失基于自身攻击力80%的生命值。"
  },
  "致命节奏": {
    "1": "【利爪专属】战斗节奏尽在掌控，攻击敌人时体力在70%以上则会获得一层攻击力、攻击速度提升2%的效果，持续10秒，至多叠加5层。（不满足则会移除所有效果）",
    "2": "【利爪专属】战斗节奏尽在掌控，攻击敌人时体力在70%以上则会获得一层攻击力、攻击速度提升3%的效果，持续10秒，至多叠加5层。（不满足则会移除所有效果）",
    "3": "【利爪专属】战斗节奏尽在掌控，攻击敌人时体力在70%以上则会获得一层攻击力、攻击速度提升4%的效果，持续10秒，至多叠加5层。（不满足则会移除所有效果）"
  },
  "舍命相搏": {
    "1": "奋力反击无暇防守，受到攻击有20%概率使自身造成的伤害提升20%， 但受到的伤害也会提升20%，持续15s。（冷却时间25s）",
    "2": "奋力反击无暇防守，受到攻击有20%概率使自身造成的伤害提升30% ，但受到的伤害也会提升30%，持续15s。（冷却时间25s）",
    "3": "奋力反击无暇防守，受到攻击有20%概率使自身造成的伤害提升40% ，但受到的伤害也会提升40%，持续15s。（冷却时间25s）"
  },
  "著名废物": {
    "3": "精神脆弱容易崩溃，最大精神降低50%。"
  },
  "蛮角庇护": {
    "1": "【蛮角专属】在生命值回满或者从濒死回到正常状态时，使自己及5米范围内的友方族人不会被造成暴击，持续8秒。（冷却时间30秒）",
    "2": "【蛮角专属】在生命值回满或者从濒死回到正常状态时，使自己及7.5米范围内的友方族人不会被造成暴击，持续10秒。（冷却时间30秒）",
    "3": "【蛮角专属】在生命值回满或者从濒死回到正常状态时，使自己及10米范围内的友方族人不会被造成暴击，持续12秒。（冷却时间30秒）"
  },
  "蛮角战魂": {
    "1": "【蛮角专属】攻击命中目标时有5%概率触发，15米范围内每名友方族人为自己提供2%伤害减免（至多5人），若为蛮角部落族人则效果提升为4%，持续20秒。（冷却时间10秒）",
    "2": "【蛮角专属】攻击命中目标时有10%概率触发，15米范围内每名友方族人为自己提供3%伤害减免（至多5人），若为蛮角部落族人则效果提升为6%，持续20秒。（冷却时间10秒）",
    "3": "【蛮角专属】攻击命中目标时有15%概率触发，15米范围内每名友方族人为自己提供4%伤害减免（至多5人），若为蛮角部落族人则效果提升为8%，持续20秒。（冷却时间10秒）"
  },
  "血上加霜": {
    "1": "贫血时会危及生命，生命值低于30%时会在10s内额外流失10%生命值。(冷却时间50s)",
    "2": "贫血时会危及生命，生命值低于30%时会在10s内额外流失15%生命值。(冷却时间50s)",
    "3": "贫血时会危及生命，生命值低于30%时会在10s内额外流失20%生命值。(冷却时间50s)"
  },
  "血液黏稠": {
    "1": "自愈能力很差，自然生命恢复降低30%。",
    "2": "自愈能力很差，自然生命恢复降低50%。",
    "3": "自愈能力很差，自然生命恢复降低70%。"
  },
  "血脉压制": {
    "1": "受到攻击时有15%概率触发，使攻击者陷入「怯战」状态，持续10秒：期间其单次伤害不会超过300点，对首领级敌人效果减弱。（冷却时间45秒）",
    "2": "受到攻击时有20%概率触发，使攻击者陷入「怯战」状态，持续10秒：期间其单次伤害不会超过300点，对首领级敌人效果减弱。（冷却时间35秒）",
    "3": "受到攻击时有25%概率触发，使攻击者陷入「怯战」状态，持续10秒：期间其单次伤害不会超过300点，对首领级敌人效果减弱。（冷却时间25秒）"
  },
  "行迹可疑": {
    "1": "行为招摇易被发现，被敌人发现时警戒增长速度提高20%。",
    "2": "行为招摇易被发现，被敌人发现时警戒增长速度提高40%。",
    "3": "行为招摇易被发现，被敌人发现时警戒增长速度提高60%。"
  },
  "誓死决心": {
    "1": "生命值低于50%时触发，无法闪避，但也不会受到任何硬直，持续15秒。（冷却时间60秒）",
    "2": "生命值低于50%时触发，无法闪避，但也不会受到任何硬直，持续20秒。（冷却时间60秒）",
    "3": "生命值低于50%时触发，无法闪避，但也不会受到任何硬直，持续25秒。（冷却时间60秒）"
  },
  "诅咒之击": {
    "1": "攻击命中目标时有5%概率触发，使其在5秒内所有天赋无法触发。（冷却时间30秒）",
    "2": "攻击命中目标时有10%概率触发，使其在7.5秒内所有天赋无法触发。（冷却时间30秒）",
    "3": "攻击命中目标时有15%概率触发，使其在10秒内所有天赋无法触发。（冷却时间30秒）"
  },
  "诡计之手": {
    "1": "在发射箭矢或者投掷物时有15%概率不消耗相应道具。",
    "2": "在发射箭矢或者投掷物时有20%概率不消耗相应道具。",
    "3": "在发射箭矢或者投掷物时有25%概率不消耗相应道具。"
  },
  "身强力壮": {
    "2": "这副躯体承受了太多太多，最大体力提升20。"
  },
  "躯干应激": {
    "1": "躯干受到攻击时有20%概率产生应激反应，接下来受到的伤害降低20%，持续5秒。(冷却时间12s)",
    "2": "躯干受到攻击时有20%概率产生应激反应，接下来受到的伤害降低30%，持续5秒。(冷却时间12s)",
    "3": "躯干受到攻击时有20%概率产生应激反应，接下来受到的伤害降低50%，持续5秒。(冷却时间12s)"
  },
  "躯干破坏": {
    "1": "熟悉躯干构造，攻击到目标躯干部位时，有20%概率伤害提升10%。",
    "2": "熟悉躯干构造，攻击到目标躯干部位时，有20%概率伤害提升15%。",
    "3": "熟悉躯干构造，攻击到目标躯干部位时，有20%概率伤害提升25%。"
  },
  "转守为攻": {
    "1": "掌握高超的弹反技巧，成功弹反敌人的近距离攻击后返还本次伤害的20%给攻击者。",
    "2": "掌握高超的弹反技巧，成功弹反敌人的近距离攻击后返还本次伤害的35%给攻击者。",
    "3": "掌握高超的弹反技巧，成功弹反敌人的近距离攻击后返还本次伤害的50%给攻击者。"
  },
  "软皮·弱挥砍": {
    "1": "难以忍受挥砍，受到挥砍类型伤害时受到的伤害提升15%。",
    "2": "难以忍受挥砍，受到挥砍类型伤害时受到的伤害提升20%。",
    "3": "难以忍受挥砍，受到挥砍类型伤害时受到的伤害提升25%。"
  },
  "软皮·弱穿刺": {
    "1": "难以抵抗戳刺，受到穿刺类型伤害时受到的伤害提升15%。",
    "2": "难以抵抗戳刺，受到穿刺类型伤害时受到的伤害提升20%。",
    "3": "难以抵抗戳刺，受到穿刺类型伤害时受到的伤害提升25%。"
  },
  "软皮·弱钝击": {
    "1": "难以承受钝击，受到钝击类型伤害时受到的伤害提升15%。",
    "2": "难以承受钝击，受到钝击类型伤害时受到的伤害提升20%。",
    "3": "难以承受钝击，受到钝击类型伤害时受到的伤害提升25%。"
  },
  "轻装速行": {
    "1": "轻装上阵脚步更加迅捷，负重达到50%之前，移动速度提升5%。",
    "2": "轻装上阵脚步更加迅捷，负重达到50%之前，移动速度提升10%。",
    "3": "轻装上阵脚步更加迅捷，负重达到50%之前，移动速度提升15%。"
  },
  "迅捷共鸣·攻": {
    "1": "攻击命中目标时有10%概率触发，提升自身「移动速度」与「攻击速度」中较低的一项，幅度为较高项的50%，持续12秒。（冷却时间60秒）",
    "2": "攻击命中目标时有15%概率触发，提升自身「移动速度」与「攻击速度」中较低的一项，幅度为较高项的50%，持续12秒。（冷却时间45秒）",
    "3": "攻击命中目标时有20%概率触发，提升自身「移动速度」与「攻击速度」中较低的一项，幅度为较高项的50%，持续12秒。（冷却时间30秒）"
  },
  "迅捷共鸣·防": {
    "1": "防御敌人攻击时有15%概率触发，提升自身「移动速度」与「攻击速度」中较低的一项，幅度为较高项的50%，持续12秒。（冷却时间60秒）",
    "2": "防御敌人攻击时有20%概率触发，提升自身「移动速度」与「攻击速度」中较低的一项，幅度为较高项的50%，持续12秒。（冷却时间45秒）",
    "3": "防御敌人攻击时有25%概率触发，提升自身「移动速度」与「攻击速度」中较低的一项，幅度为较高项的50%，持续12秒。（冷却时间30秒）"
  },
  "迅捷流转·攻": {
    "1": "攻击命中目标时有5%概率触发，将当前25%的「移速」转化为「攻速」，持续12秒。（冷却时间60秒）",
    "2": "攻击命中目标时有10%概率触发，将当前25%的「移速」转化为「攻速」，持续12秒。（冷却时间45秒）",
    "3": "攻击命中目标时有15%概率触发，将当前25%的「移速」转化为「攻速」，持续12秒。（冷却时间30秒）"
  },
  "迅捷流转·防": {
    "1": "防御敌人攻击时有10%概率触发，将当前25%的「攻速」转化为「移速」，持续12秒。（冷却时间60秒）",
    "2": "防御敌人攻击时有15%概率触发，将当前25%的「攻速」转化为「移速」，持续12秒。（冷却时间45秒）",
    "3": "防御敌人攻击时有20%概率触发，将当前25%的「攻速」转化为「移速」，持续12秒。（冷却时间30秒）"
  },
  "近视": {
    "1": "眼神很差，视野距离降低3米。",
    "2": "眼神很差，视野距离降低5米。",
    "3": "眼神很差，视野距离降低10米。"
  },
  "这味对咯": {
    "2": "嗯，就这个味道，刺激却令人陶醉，身上沾满粪便更加兴奋，食用时会获得40点心情值，并在15分钟内心情值下降速率降低50%，获得心情值时提升100%。"
  },
  "远程打击": {
    "1": "距离拉开攻势更猛，对15米外敌人造成的伤害提升3%。",
    "2": "距离拉开攻势更猛，对15米外敌人造成的伤害提升6%。",
    "3": "距离拉开攻势更猛，对15米外敌人造成的伤害提升9%。"
  },
  "远视": {
    "1": "视力非凡，视野距离提升3米。",
    "2": "视力非凡，视野距离提升5米。",
    "3": "视力非凡，视野距离提升10米。"
  },
  "连锁闪避": {
    "1": "成功闪避敌人攻击后，在接下来的2秒内能够额外免疫一次攻击伤害。（冷却时间5秒）",
    "2": "成功闪避敌人攻击后，在接下来的3秒内能够额外免疫一次攻击伤害。（冷却时间5秒）",
    "3": "成功闪避敌人攻击后，在接下来的4秒内能够额外免疫一次攻击伤害。（冷却时间5秒）"
  },
  "迷惑弹反": {
    "1": "弹反敌人攻击时，使其「迷惑」在6秒内视角操作反转。（冷却时间25秒）",
    "2": "弹反敌人攻击时，使其「迷惑」在8秒内视角操作反转。（冷却时间25秒）",
    "3": "弹反敌人攻击时，使其「迷惑」在10秒内视角操作反转。（冷却时间25秒）"
  },
  "迷惑防御": {
    "1": "防御敌人攻击时有5%概率触发，使其「迷惑」在5秒内视角操作反转。（冷却时间20秒）",
    "2": "防御敌人攻击时有10%概率触发，使其「迷惑」在5秒内视角操作反转。（冷却时间20秒）",
    "3": "防御敌人攻击时有15%概率触发，使其「迷惑」在5秒内视角操作反转。（冷却时间20秒）"
  },
  "送葬者": {
    "3": "攻击生命值低于30%或处于濒死状态的敌人会让自己兴奋，有25%概率短暂提升攻击力20%、增加移速20%、攻击速度10%，持续8s。（冷却时间30s）"
  },
  "逃脱宿命": {
    "2": "生命值低于15%或濒死时若受到敌人的攻击，敌人有可能遭受天谴。（冷却时间15s）"
  },
  "逆闪弹反": {
    "1": "弹反敌人攻击时，使其「逆闪」在6秒内闪避方向翻转。（冷却时间25秒）",
    "2": "弹反敌人攻击时，使其「逆闪」在8秒内闪避方向翻转。（冷却时间25秒）",
    "3": "弹反敌人攻击时，使其「逆闪」在10秒内闪避方向翻转。（冷却时间25秒）"
  },
  "逆闪防御": {
    "1": "防御敌人攻击时有5%概率触发，使其「逆闪」在5秒内闪避方向翻转。（冷却时间20秒）",
    "2": "防御敌人攻击时有10%概率触发，使其「逆闪」在5秒内闪避方向翻转。（冷却时间20秒）",
    "3": "防御敌人攻击时有15%概率触发，使其「逆闪」在5秒内闪避方向翻转。（冷却时间20秒）"
  },
  "避实击虚": {
    "1": "成功闪避敌人攻击后，短时间内增加10%移动速度、攻击速度、提升5%攻击力，持续 5s。(冷却时间10s)",
    "2": "成功闪避敌人攻击后，短时间内增加20%移动速度、攻击速度、提升7.5%攻击力，持续 5s。(冷却时间10s)",
    "3": "成功闪避敌人攻击后，短时间内增加30%移动速度、攻击速度、提升10%攻击力，持续 5s。(冷却时间10s)"
  },
  "避开要害": {
    "1": "【火石专属】距离越远的攻击对自己威胁越小，受到来自10米外的攻击时，有20%的概率使本次受到的伤害降低30%。",
    "2": "【火石专属】距离越远的攻击对自己威胁越小，受到来自10米外的攻击时，有20%的概率使本次受到的伤害降低50%。",
    "3": "【火石专属】距离越远的攻击对自己威胁越小，受到来自10米外的攻击时，有20%的概率使本次受到的伤害降低80%。"
  },
  "部落·体力炎热抗性": {
    "1": "久居炎热地带的蛮角族人产生了天然抗性，炎热抗性提升5，最大体力增加10，削韧防御提升3%。",
    "2": "久居炎热地带的蛮角族人产生了天然抗性，炎热抗性提升10，最大体力增加15，削韧防御提升6%。",
    "3": "久居炎热地带的蛮角族人产生了天然抗性，炎热抗性提升15，最大体力增加20，削韧防御提升10%。"
  },
  "部落·体力辐射抗性": {
    "1": "久居辐射地带的蛮角族人产生了天然抗性，辐射抗性提升5，最大体力增加10，削韧防御提升3%。",
    "2": "久居辐射地带的蛮角族人产生了天然抗性，辐射抗性提升10，最大体力增加15，削韧防御提升6%。",
    "3": "久居辐射地带的蛮角族人产生了天然抗性，辐射抗性提升15，最大体力增加20，削韧防御提升10%。"
  },
  "部落·侵袭之力": {
    "1": "身为利爪部落族人，对火石部落、毒牙部落、流放者、掠夺者造成的伤害提升2%。",
    "2": "身为利爪部落族人，对火石部落、毒牙部落、流放者、掠夺者造成的伤害提升5%。",
    "3": "身为利爪部落族人，对火石部落、毒牙部落、流放者、掠夺者造成的伤害提升8%。"
  },
  "部落·免伤炎热抗性": {
    "1": "久居炎热地带的蛮角族人产生了天然抗性，炎热抗性提升5，伤害减免提升4%，攻击附加昏迷伤害2。",
    "2": "久居炎热地带的蛮角族人产生了天然抗性，炎热抗性提升10，伤害减免提升6%，攻击附加昏迷伤害4。",
    "3": "久居炎热地带的蛮角族人产生了天然抗性，炎热抗性提升15，伤害减免提升8%，攻击附加昏迷伤害6。"
  },
  "部落·免伤辐射抗性": {
    "1": "久居辐射地带的蛮角族人产生了天然抗性，辐射抗性提升5，伤害减免提升4%，攻击附加昏迷伤害2。",
    "2": "久居辐射地带的蛮角族人产生了天然抗性，辐射抗性提升10，伤害减免提升6%，攻击附加昏迷伤害4。",
    "3": "久居辐射地带的蛮角族人产生了天然抗性，辐射抗性提升15，伤害减免提升8%，攻击附加昏迷伤害6。"
  },
  "部落·坚韧之力": {
    "1": "身为火石部落族人，最大韧性永久提高15点。",
    "2": "身为火石部落族人，最大韧性永久提高20点",
    "3": "身为火石部落族人，最大韧性永久提高25点。"
  },
  "部落·坚韧寒冷抗性": {
    "1": "长期生活在雪山的火石族人产生了天然抗性，寒冷抗性提升5，最大韧性提升15。",
    "2": "长期生活在雪山的火石族人产生了天然抗性，寒冷抗性提升10，最大韧性提升20。",
    "3": "长期生活在雪山的火石族人产生了天然抗性，寒冷抗性提升15，最大韧性提升25。"
  },
  "部落·坚韧炎热抗性": {
    "1": "长期生活在火山的火石族人产生了天然抗性，炎热抗性提升5，最大韧性提升15。",
    "2": "长期生活在火山的火石族人产生了天然抗性，炎热抗性提升10，最大韧性提升20。",
    "3": "长期生活在火山的火石族人产生了天然抗性，炎热抗性提升15，最大韧性提升25。"
  },
  "部落·坚韧辐射抗性": {
    "1": "长期生活在荒原的火石族人产生了天然抗性，辐射抗性提升5，最大韧性提升15。",
    "2": "长期生活在荒原的火石族人产生了天然抗性，辐射抗性提升10，最大韧性提升20。",
    "3": "长期生活在荒原的火石族人产生了天然抗性，辐射抗性提升15，最大韧性提升25。"
  },
  "部落·增伤炎热抗性": {
    "1": "久居炎热地带的荒狼族人产生了天然抗性，炎热抗性提升5，伤害提升4%，攻击附加流血伤害2。",
    "2": "久居炎热地带的荒狼族人产生了天然抗性，炎热抗性提升10，伤害提升6%，攻击附加流血伤害4。",
    "3": "久居炎热地带的荒狼族人产生了天然抗性，炎热抗性提升15，伤害提升8%，攻击附加流血伤害6。"
  },
  "部落·增伤辐射抗性": {
    "1": "久居辐射地带的荒狼族人产生了天然抗性，辐射抗性提升5，伤害提升4%，攻击附加流血伤害2。",
    "2": "久居辐射地带的荒狼族人产生了天然抗性，辐射抗性提升10，伤害提升6%，攻击附加流血伤害4。",
    "3": "久居辐射地带的荒狼族人产生了天然抗性，辐射抗性提升15，伤害提升8%，攻击附加流血伤害6。"
  },
  "部落·幸存者": {
    "2": "身为部落战争的幸存者，拥有力量才能在这片土地生存，最大负重提高20%。"
  },
  "部落·抵御之力": {
    "1": "身为火石部落族人，防御力永久提升3%。",
    "2": "身为火石部落族人，防御力永久提升6%。",
    "3": "身为火石部落族人，防御力永久提升9%。"
  },
  "部落·暴伤寒冷抗性": {
    "1": "长期生活在雪山的利爪族人产生了天然抗性，寒冷抗性提升5，暴击伤害提升6%。 ",
    "2": "长期生活在雪山的利爪族人产生了天然抗性，寒冷抗性提升10，暴击伤害提升8%。 ",
    "3": "长期生活在雪山的利爪族人产生了天然抗性，寒冷抗性提升15，暴击伤害提升10%。 "
  },
  "部落·暴伤炎热抗性": {
    "1": "长期生活在火山的利爪族人产生了天然抗性，炎热抗性提升5，暴击伤害提升6%。 ",
    "2": "长期生活在火山的利爪族人产生了天然抗性，炎热抗性提升10，暴击伤害提升8%。 ",
    "3": "长期生活在火山的利爪族人产生了天然抗性，炎热抗性提升15，暴击伤害提升10%。"
  },
  "部落·暴伤辐射抗性": {
    "1": "长期生活在荒原的利爪族人产生了天然抗性，辐射抗性提升5，暴击伤害提升6%。 ",
    "2": "长期生活在荒原的利爪族人产生了天然抗性，辐射抗性提升10，暴击伤害提升8%。 ",
    "3": "长期生活在荒原的利爪族人产生了天然抗性，辐射抗性提升15，暴击伤害提升10%。 "
  },
  "部落·暴击之力": {
    "1": "身为利爪部落族人，暴击率永久提升2%。",
    "2": "身为利爪部落族人，暴击率永久提升5%。",
    "3": "身为利爪部落族人，暴击率永久提升8%。"
  },
  "部落·暴击寒冷抗性": {
    "1": "长期生活在雪山的利爪族人产生了天然抗性，寒冷抗性提升5，暴击率提升2%。",
    "2": "长期生活在雪山的利爪族人产生了天然抗性，寒冷抗性提升10，暴击率提升5%。",
    "3": "长期生活在雪山的利爪族人产生了天然抗性，寒冷抗性提升15，暴击率提升8%。"
  },
  "部落·暴击炎热抗性": {
    "1": "长期生活在火山的利爪族人产生了天然抗性，炎热抗性提升5，暴击率提升2%。",
    "2": "长期生活在火山的利爪族人产生了天然抗性，炎热抗性提升10，暴击率提升5%。",
    "3": "长期生活在火山的利爪族人产生了天然抗性，炎热抗性提升15，暴击率提升8%。"
  },
  "部落·暴击辐射抗性": {
    "1": "长期生活在荒原的利爪族人产生了天然抗性，辐射抗性提升5，暴击率提升2%。",
    "2": "长期生活在荒原的利爪族人产生了天然抗性，辐射抗性提升10，暴击率提升5%。",
    "3": "长期生活在荒原的利爪族人产生了天然抗性，辐射抗性提升15，暴击率提升8%。"
  },
  "部落·暴抗之力": {
    "1": "身为火石部落族人，暴击抵抗永久提升3%。",
    "2": "身为火石部落族人，暴击抵抗永久提升6%。",
    "3": "身为火石部落族人，暴击抵抗永久提升9%。"
  },
  "部落·毒免寒冷抗性": {
    "1": "长期生活在雪山的毒牙族人产生了天然抗性，寒冷抗性提升5，受到的毒素伤害降低15%。",
    "2": "长期生活在雪山的毒牙族人产生了天然抗性，寒冷抗性提升10，受到的毒素伤害降低20%。",
    "3": "长期生活在雪山的毒牙族人产生了天然抗性，寒冷抗性提升15，受到的毒素伤害降低25%。"
  },
  "部落·毒免炎热抗性": {
    "1": "长期生活在火山的毒牙族人产生了天然抗性，炎热抗性提升5，受到的毒素伤害降低15%。",
    "2": "长期生活在火山的毒牙族人产生了天然抗性，炎热抗性提升10，受到的毒素伤害降低20%。",
    "3": "长期生活在火山的毒牙族人产生了天然抗性，炎热抗性提升15，受到的毒素伤害降低25%。"
  },
  "部落·毒素免疫": {
    "1": "身为毒牙部落族人，受到的毒素伤害永久降低15%。",
    "2": "身为毒牙部落族人，受到的毒素伤害永久降低20%。",
    "3": "身为毒牙部落族人，受到的毒素伤害永久降低25%。"
  },
  "部落·毒素寒冷抗性": {
    "1": "长期生活在雪山的毒牙族人产生了天然抗性，寒冷抗性提升5，毒素抗性提升5。",
    "2": "长期生活在雪山的毒牙族人产生了天然抗性，寒冷抗性提升10，毒素抗性提升10。",
    "3": "长期生活在雪山的毒牙族人产生了天然抗性，寒冷抗性提升15，毒素抗性提升15。"
  },
  "部落·毒素抵抗": {
    "1": "身为毒牙部落族人，毒抗永久提升20。",
    "2": "身为毒牙部落族人，毒抗永久提升25。",
    "3": "身为毒牙部落族人，毒抗永久提升30。"
  },
  "部落·毒素炎热抗性": {
    "1": "长期生活在火山的毒牙族人产生了天然抗性，炎热抗性提升5，毒素抗性提升5。",
    "2": "长期生活在火山的毒牙族人产生了天然抗性，炎热抗性提升10，毒素抗性提升10。",
    "3": "长期生活在火山的毒牙族人产生了天然抗性，炎热抗性提升15，毒素抗性提升15。"
  },
  "部落·毒素辐射抗性": {
    "1": "长期生活在荒原的毒牙族人产生了天然抗性，辐射抗性提升5，受到的毒素伤害降低15%。",
    "2": "长期生活在荒原的毒牙族人产生了天然抗性，辐射抗性提升10，受到的毒素伤害降低20%。",
    "3": "长期生活在荒原的毒牙族人产生了天然抗性，辐射抗性提升15，受到的毒素伤害降低25%。"
  },
  "部落·狂野之力": {
    "1": "身为利爪部落族人，暴击伤害永久提升6%。",
    "2": "身为利爪部落族人，暴击伤害永久提升8%。",
    "3": "身为利爪部落族人，暴击伤害永久提升10%。"
  },
  "部落·耐力炎热抗性": {
    "1": "久居炎热地带的荒狼族人产生了天然抗性，炎热抗性提升5，恢复体力时恢复量提升5%，攻击附加麻痹伤害2。",
    "2": "久居炎热地带的荒狼族人产生了天然抗性，炎热抗性提升10，恢复体力时恢复量提升10%，攻击附加麻痹伤害4。",
    "3": "久居炎热地带的荒狼族人产生了天然抗性，炎热抗性提升15，恢复体力时恢复量提升15%，攻击附加麻痹伤害6。"
  },
  "部落·耐力辐射抗性": {
    "1": "久居辐射地带的荒狼族人产生了天然抗性，辐射抗性提升5，恢复体力时恢复量提升5%，攻击附加麻痹伤害2。",
    "2": "久居辐射地带的荒狼族人产生了天然抗性，辐射抗性提升10，恢复体力时恢复量提升10%，攻击附加麻痹伤害4。",
    "3": "久居辐射地带的荒狼族人产生了天然抗性，辐射抗性提升15，恢复体力时恢复量提升15%，攻击附加麻痹伤害6。"
  },
  "部落·荒狼之力": {
    "1": "荒狼部落的族人冷血无情，伤害提升4%，攻击附加流血伤害2。",
    "2": "荒狼部落的族人冷血无情，伤害提升6%，攻击附加流血伤害4。",
    "3": "荒狼部落的族人冷血无情，伤害提升8%，攻击附加流血伤害6。"
  },
  "部落·荒狼之息": {
    "1": "荒狼部落的族人耐力非凡，在恢复体力时恢复量提升5%，攻击附加麻痹伤害2。",
    "2": "荒狼部落的族人耐力非凡，在恢复体力时恢复量提升10%，攻击附加麻痹伤害4。",
    "3": "荒狼部落的族人耐力非凡，在恢复体力时恢复量提升15%，攻击附加麻痹伤害6。"
  },
  "部落·蛮角之力": {
    "1": "蛮角部落的族人稳重强壮，伤害减免提升4%，攻击附加昏迷伤害2。",
    "2": "蛮角部落的族人稳重强壮，伤害减免提升6%，攻击附加昏迷伤害4。",
    "3": "蛮角部落的族人稳重强壮，伤害减免提升8%，攻击附加昏迷伤害6。"
  },
  "部落·蛮角之息": {
    "1": "蛮角部落族人有着顽强的意志，最大体力增加10，削韧防御提升3%。",
    "2": "蛮角部落族人有着顽强的意志，最大体力增加15，削韧防御提升6%。",
    "3": "蛮角部落族人有着顽强的意志，最大体力增加20，削韧防御提升10%。"
  },
  "部落·防御寒冷抗性": {
    "1": "长期生活在雪山的火石族人产生了天然抗性，寒冷抗性提升5，防御力提升3%。",
    "2": "长期生活在雪山的火石族人产生了天然抗性，寒冷抗性提升10，防御力提升6%。",
    "3": "长期生活在雪山的火石族人产生了天然抗性，寒冷抗性提升15，防御力提升9%。"
  },
  "部落·防御炎热抗性": {
    "1": "长期生活在火山的火石族人产生了天然抗性，炎热抗性提升5，防御力提升3%。",
    "2": "长期生活在火山的火石族人产生了天然抗性，炎热抗性提升10，防御力提升6%。",
    "3": "长期生活在火山的火石族人产生了天然抗性，炎热抗性提升15，防御力提升9%。"
  },
  "部落·防御辐射抗性": {
    "1": "长期生活在荒原的火石族人产生了天然抗性，辐射抗性提升5，防御力提升3%。",
    "2": "长期生活在荒原的火石族人产生了天然抗性，辐射抗性提升10，防御力提升6%。",
    "3": "长期生活在荒原的火石族人产生了天然抗性，辐射抗性提升15，防御力提升9%。"
  },
  "醉意感应": {
    "1": "酒醉人不醉，在饮用酒类道具后的15秒内可自动闪避1次攻击，喜好饮酒者会获得更多次数，次数耗尽效果即清除（冷却时间30秒）。",
    "2": "酒醉人不醉，在饮用酒类道具后的15秒内可自动闪避2次攻击，喜好饮酒者会获得更多次数，次数耗尽效果即清除（冷却时间30秒）。",
    "3": "酒醉人不醉，在饮用酒类道具后的15秒内可自动闪避3次攻击，喜好饮酒者会获得更多次数，次数耗尽效果即清除（冷却时间30秒）。"
  },
  "重整旗鼓": {
    "1": "处于濒死状态时，附近有敌人进入濒死或死亡可使自己立即脱离濒死状态。",
    "2": "处于濒死状态时，附近有敌人进入濒死或死亡可使自己立即脱离濒死状态，并额外恢复10%生命。",
    "3": "处于濒死状态时，附近有敌人进入濒死或死亡可使自己立即脱离濒死状态，并额外恢复20%生命。"
  },
  "重装奔袭": {
    "1": "背负重物脚步更加迅捷，负重达到90%之后，移动速度提升10%。",
    "2": "背负重物脚步更加迅捷，负重达到90%之后，移动速度提升20%。",
    "3": "背负重物脚步更加迅捷，负重达到90%之后，移动速度提升40%。"
  },
  "野性觉醒": {
    "1": "生命受到威胁时会唤起内心的野性，生命值低于30%时攻击力提升10%且每秒回复10点体力，但自身防御力也会降低20%，持续时间15s。(冷却时间30s)",
    "2": "生命受到威胁时会唤起内心的野性，生命值低于30%时攻击力提升15%且每秒回复15点体力，但自身防御力也会降低20%，持续时间15s。(冷却时间30s)",
    "3": "生命受到威胁时会唤起内心的野性，生命值低于30%时攻击力提升20%且每秒回复20点体力，但自身防御力也会降低20%，持续时间15s。(冷却时间30s)"
  },
  "钟爱动物": {
    "3": "附近存在任何动物时都会感到愉快，每隔一段时间获得60点心情值，并在15分钟内心情值下降速率降低70%，获得心情值时提升125%。（在此期间可使心情达到非常愉快状态）"
  },
  "钟爱巨象": {
    "3": "附近有巨象时会感到愉快，每隔一段时间获得60点心情值，并在15分钟内心情值下降速率降低70%，获得心情值时提升125%。（在此期间可使心情达到非常愉快状态）"
  },
  "钟爱河马": {
    "3": "附近有河马时会感到愉快，每隔一段时间获得60点心情值，并在15分钟内心情值下降速率降低70%，获得心情值时提升125%。（在此期间可使心情达到非常愉快状态）"
  },
  "钟爱火烈鸟": {
    "3": "附近有火烈鸟时会感到愉快，每隔一段时间获得60点心情值，并在15分钟内心情值下降速率降低70%，获得心情值时提升125%。（在此期间可使心情达到非常愉快状态）"
  },
  "钟爱犀牛": {
    "3": "附近有犀牛时会感到愉快，每隔一段时间获得60点心情值，并在15分钟内心情值下降速率降低70%，获得心情值时提升125%。（在此期间可使心情达到非常愉快状态）"
  },
  "钟爱犰狳蜥": {
    "3": "附近有犰狳蜥时会感到愉快，每隔一段时间获得60点心情值，并在15分钟内心情值下降速率降低70%，获得心情值时提升125%。（在此期间可使心情达到非常愉快状态）"
  },
  "钟爱猴子": {
    "3": "活泼灵动的猴子总是能让人开心，附近有猴子存在时每隔一段时间会获得60点心情值，并在15分钟内心情值下降速率降低70%，获得心情值时提升125%。（在此期间可使心情达到非常愉快状态）"
  },
  "钟爱羊驼和大羊驼": {
    "3": "对羊驼和大羊驼情有独钟，附近有此类动物存在时每隔一段时间会获得60点心情值，并在15分钟内心情值下降速率降低70%，获得心情值时提升125%。（在此期间可使心情达到非常愉快状态）"
  },
  "钟爱象龟": {
    "3": "附近有象龟时会感到愉快，每隔一段时间获得60点心情值，并在15分钟内心情值下降速率降低70%，获得心情值时提升125%。（在此期间可使心情达到非常愉快状态）"
  },
  "钟爱豹子": {
    "3": "对豹子情有独钟，附近有豹子存在时每隔一段时间会获得60点心情值，并在15分钟内心情值下降速率降低70%，获得心情值时提升125%。（在此期间可使心情达到非常愉快状态）"
  },
  "钟爱野猪": {
    "3": "附近有野猪时会感到愉快，每隔一段时间获得60点心情值，并在15分钟内心情值下降速率降低70%，获得心情值时提升125%。（在此期间可使心情达到非常愉快状态）"
  },
  "钟爱长角牛": {
    "3": "附近有长角牛时会感到愉快，每隔一段时间获得60点心情值，并在15分钟内心情值下降速率降低70%，获得心情值时提升125%。（在此期间可使心情达到非常愉快状态）"
  },
  "钟爱食人鱼": {
    "3": "附近有食人鱼时会感到愉快，每隔一段时间获得60点心情值，并在15分钟内心情值下降速率降低70%，获得心情值时提升125%。（在此期间可使心情达到非常愉快状态）"
  },
  "钟爱驴": {
    "3": "附近有驴时会感到愉快，每隔一段时间获得60点心情值，并在15分钟内心情值下降速率降低70%，获得心情值时提升125%。（在此期间可使心情达到非常愉快状态）"
  },
  "钟爱骆驼": {
    "3": "附近有骆驼时会感到愉快，每隔一段时间获得60点心情值，并在15分钟内心情值下降速率降低70%，获得心情值时提升125%。（在此期间可使心情达到非常愉快状态）"
  },
  "钟爱鸡": {
    "3": "附近有鸡时会感到愉快，每隔一段时间获得60点心情值，并在15分钟内心情值下降速率降低70%，获得心情值时提升125%。（在此期间可使心情达到非常愉快状态）"
  },
  "钟爱鸵鸟": {
    "3": "对鸵鸟情有独钟，附近有鸵鸟存在时每隔一段时间会获得60点心情值，并在15分钟内心情值下降速率降低70%，获得心情值时提升125%。（在此期间可使心情达到非常愉快状态）"
  },
  "钟爱鹦鹉": {
    "3": "漂亮灵性的鹦鹉让人着迷，附近有鹦鹉存在时每隔一段时间会获得60点心情值，并在15分钟内心情值下降速率降低70%，获得心情值时提升125%。（在此期间可使心情达到非常愉快状态）"
  },
  "钢铁之躯": {
    "1": "受到攻击时若当前韧性超过70%则免疫本次硬直。",
    "2": "受到攻击时若当前韧性超过60%则免疫本次硬直。",
    "3": "受到攻击时若当前韧性超过50%则免疫本次硬直。"
  },
  "锥骨之伤": {
    "1": "【猎手专属】有些伤痛不会立即显现，使用远程武器命中目标时有5%概率施加一道持续5s的隐藏伤口，在此期冲刺时会感到昏迷。",
    "2": "【猎手专属】有些伤痛不会立即显现，使用远程武器命中目标时有10%概率施加一道持续5s的隐藏伤口，在此期间冲刺时会感到昏迷。",
    "3": "【猎手专属】有些伤痛不会立即显现，使用远程武器命中目标时有15%概率施加一道持续5s的隐藏伤口，在此期间冲刺时会感到昏迷。"
  },
  "锻器专注": {
    "1": "【匠人专属】锻造武器时异常专注，产出高品质概率提升5%。",
    "2": "【匠人专属】锻造武器时异常专注，产出高品质概率提升7.5%。",
    "3": "【匠人专属】锻造武器时异常专注，产出高品质概率提升10%。"
  },
  "镇压者": {
    "3": "攻击命中时有15%概率触发，使其陷入「怯战」状态，持续15秒：期间其单次伤害不会超过300点。此伤害限制会受到施加者与被施加者的「部落地位」影响。（冷却时间30秒）"
  },
  "长矛减伤": {
    "1": "使用长矛威胁减弱，使用矛类武器造成的伤害降低10%。",
    "2": "使用长矛威胁减弱，使用矛类武器造成的伤害降低15%。",
    "3": "使用长矛威胁减弱，使用矛类武器造成的伤害降低20%。"
  },
  "长矛增伤": {
    "1": "使用长矛威力更强，长矛类武器造成的伤害提升3%。",
    "2": "使用长矛威力更强，长矛类武器造成的伤害提升6%。",
    "3": "使用长矛威力更强，长矛类武器造成的伤害提升9%。"
  },
  "闪避投掷": {
    "1": "进行闪避时触发自动投掷，消耗快捷栏中的飞斧、飞刀或掷矛，攻击10米内的敌人。",
    "2": "进行闪避时触发自动投掷，消耗快捷栏中的飞斧、飞刀或掷矛，攻击15米内的敌人。",
    "3": "进行闪避时触发自动投掷，消耗快捷栏中的飞斧、飞刀或掷矛，攻击15米内的敌人，若命中目标使其减速50%，持续5秒。"
  },
  "防具制造加速": {
    "1": "【匠人专属】精通甲胄工艺，完成防具制造任务的时间缩短10%。",
    "2": "【匠人专属】精通甲胄工艺，完成防具制造任务的时间缩短20%。",
    "3": "【匠人专属】精通甲胄工艺，完成防具制造任务的时间缩短30%。"
  },
  "防具精修": {
    "1": "【蛮角专属】身为匠人修理护甲的耐久损耗降低20%。",
    "2": "【蛮角专属】身为匠人修理护甲的耐久损耗降低35%。",
    "3": "【蛮角专属】身为匠人修理护甲的耐久损耗降低50%。"
  },
  "防御强袭": {
    "1": "防御敌人攻击后，使接下来1秒内的攻击忽视敌人防御力。（冷却时间20秒）",
    "2": "防御敌人攻击后，使接下来2秒内的攻击忽视敌人防御力。（冷却时间20秒）",
    "3": "防御敌人攻击后，使接下来3秒内的攻击忽视敌人防御力。（冷却时间20秒）"
  },
  "防御窃取": {
    "1": "【卫士专属】攻击命中目标时有5%概率触发，窃取目标当前10%防御（至多40点），转化为自身的提升，持续12秒，至多叠加5层。",
    "2": "【卫士专属】攻击命中目标时有10%概率触发，窃取目标当前10%防御（至多40点），转化为自身的提升，持续12秒，至多叠加5层。",
    "3": "【卫士专属】攻击命中目标时有15%概率触发，窃取目标当前10%防御（至多40点），转化为自身的提升，持续12秒，至多叠加5层。"
  },
  "震荡弹反": {
    "1": "弹反敌人攻击时，使其「麻木」在6秒内无法防御。（冷却时间25秒）",
    "2": "弹反敌人攻击时，使其「麻木」在8秒内无法防御。（冷却时间25秒）",
    "3": "弹反敌人攻击时，使其「麻木」在10秒内无法防御。（冷却时间25秒）"
  },
  "震荡防御": {
    "1": "防御敌人攻击时有5%概率触发，使其「麻木」在5秒内无法防御。（冷却时间20秒）",
    "2": "防御敌人攻击时有10%概率触发，使其「麻木」在5秒内无法防御。（冷却时间20秒）",
    "3": "防御敌人攻击时有15%概率触发，使其「麻木」在5秒内无法防御。（冷却时间20秒）"
  },
  "霸体崩解": {
    "1": "弹反敌人攻击时有20%概率触发，移除其霸体状态。（冷却时间15秒）",
    "2": "弹反敌人攻击时有30%概率触发，移除其霸体状态并使其2秒内无法获得霸体。（冷却时间15秒）",
    "3": "弹反敌人攻击时有40%概率触发，移除其霸体状态并使其3秒内无法获得霸体。（冷却时间15秒）"
  },
  "静态恢复": {
    "1": "生命在于静止，15秒内没有任何移动身体即会缓慢恢复，每秒恢复基于自身防御力15%的生命值。",
    "2": "生命在于静止，15秒内没有任何移动身体即会缓慢恢复，每秒恢复基于自身防御力20%的生命值。",
    "3": "生命在于静止，15秒内没有任何移动身体即会缓慢恢复，每秒恢复基于自身防御力25%的生命值。"
  },
  "飞刀刺客": {
    "3": "曾用一把飞刀数米外击中部落头目使其流血而亡，一战成名，命中目标时能够对其造成每秒基于自身攻击力20%的流血效果，持续10s，可叠加。"
  },
  "饮血者": {
    "3": "以血养身，对近距离目标造成的流血伤害，其中40%转化为生命恢复，若自身处于流血状态则效果提升为80%。"
  },
  "驼牛": {
    "1": "对背负重物颇有心得，最大负重提升20%。",
    "2": "对背负重物颇有心得，最大负重提升40%。",
    "3": "对背负重物颇有心得，最大负重提升60%。"
  },
  "鲜血吸收": {
    "1": "饮血充饥，对5米内的目标造成伤害时，有5%概率使其额外流失最大生命的3%（至多100点）并为攻击者恢复等量生命值。若目标处于流血状态，则效果提升至5%（至多150点）。",
    "2": "饮血充饥，对5米内的目标造成伤害时，有10%概率使其额外流失最大生命的3%（至多100点）并为攻击者恢复等量生命值。若目标处于流血状态，则效果提升至5%（至多150点）。",
    "3": "饮血充饥，对5米内的目标造成伤害时，有15%概率使其额外流失最大生命的3%（至多100点）并为攻击者恢复等量生命值。若目标处于流血状态，则效果提升至5%（至多150点）。"
  }
}